{
  "total_samples": 1,
  "categorized_samples": {
    "trend": [
      {
        "sample_id": "unknown",
        "summary": "神火股份（000933）公司三季报业绩大幅改善，扣非后净利润同比增长203%，主要得益于云南神火并表驱动增长。公司优化产业结构，煤铝主业经营改善明显，新疆神火、泉店煤矿增利显著，同时原材料价格下降进一步降低成本。云南神火完成并表后，集团计划在未来六个月内增持不超过1.5%的股份，显示出对未来业绩增长的信心。近期市场数据显示，股票价格波动较大，但整体趋势向上。预测结果显示，该股票下个月最终收益为‘涨’，上涨概率为‘极大’。",
        "content": "研报题目是:神火股份（000933）公司三季报点评报告：扣非后业绩同比大幅改善，集团增持彰显未来信心；目标价格是目标价格未公布，评分是7.0；研报摘要:神火股份 000933 事件 公司发布 2020 年三季报， 2020Q1 Q3 实现扣非后归母净利润 2 99 亿元，较 2019 年同期 调整前， 亏损 2 91 亿元 增加 5 91 亿元，增幅达 203 实现归母净利润 4 93 亿元，较 2019 年同期 调整前 减少 80 4 。2020Q3 单季业绩大幅改善，云南神火并表驱动未来成长2020 年前三季度公司归母净利同比降幅明显，主因 2019Q3 回收高家庄煤矿 24 6亿元转让款确认大额资产处置收益，抬高基数。扣非后来看， 2020Q3 单季扣非后归母净利润为 1 52 亿元，在 2019 年同期 0 42 亿元基础上增加 1 99 亿元， 且超过上半年扣非业绩总和， 公司近年来积极优化产业结构成效显著，煤铝主业经营均明显改善。 未来梁北矿扩产有序推进 云南神火预计 2021 年初完全通电后将贡献全年业绩。考虑到云南神火通电后盈利超预期，且公司权益比例提升，我们上调盈利预测，预计 2020 2021 2022 年归母净利润 7 3 0 5 12 8 2 9 15 9 3 1 亿 元 ， 同 比 45 8 75 4 23 8 EPS 为 0 38 0 02 0 67 0 15 0 83 0 16 元， 对应当前股价 PE 分别为 13 9x 7 9x 6 4x。 维持 买入 评级。煤、铝主业经营状况明显改善，新疆神火、泉店煤矿大幅增利受益原材料价格下降，新疆神火同比增利 3 亿元。 前三季度新疆神火实现利润7 75 亿元，同比增加 3 95 亿元，其中三季度实现 3 84 亿元，环比增加 1 88 亿元。氧化铝、阳极炭块价格下降致吨铝完全成本同比减少 760 元 吨。 煤价走强，泉店矿增利 0 63 亿元。 泉店矿是公司产能最大的在产煤矿，前三季度吨煤价格同比 73 7 元 吨，吨煤成本同比 23 3 元 吨。 本部氧化铝产能出清，汇源铝业关停业绩减亏 1 92 亿元。 公司于 2019 年底关停汇源铝业 80 万吨亏损产能，经营利润同比减亏 2 59 亿元。 总体来看，煤铝主业经营状况明显改善。云南神火完成并表满产在即， 集团增持股份彰显信心公司 9 月对云南神火完成并表，持股比例由 32 2 增至 43 4 ，权益增加将增厚项目业绩贡献。 一系列 45 万吨已于 9 月初完全通电， 年内可贡献约 30 万吨产量， 二系列 45 万吨预计 2021Q1 完全通电，可几乎贡献全年业绩。 煤炭方面，梁北矿技改扩产预计年底试运营，产能将新增 150 万吨。同时，集团拟在半年内增持不超过 1 5 股份，凸显了对公司未来业绩前景的信心与对投资价值的认可。风险提示 煤、铝价格下跌超预期 煤矿停减产风险 云南项目进展不及预期。同时，下面我提供的一份该股票的近期市场数据， 提示:我提供的数据一般是由三个字段组成，分别是每个对应日期的股票价格，涨跌幅，成交量数据。 数据如下: 1.该企业的近期数据如下:1.股票价格（元）:{'2020-10-09': 4.84, '2020-10-12': 4.98, '2020-10-13': 4.94, '2020-10-14': 4.88, '2020-10-15': 4.94, '2020-10-16': 5.25, '2020-10-19': 5.39, '2020-10-20': 5.39, '2020-10-21': 5.43, '2020-10-22': 5.32, '2020-10-23': 5.31, '2020-10-26': 5.25, '2020-10-27': 5.18, '2020-10-28': 5.32, '2020-10-29': 5.18, '2020-10-30': 5.09}; 2.日涨跌幅（%）:{'2020-10-09': 4.7619, '2020-10-12': 2.8926, '2020-10-13': -0.8032, '2020-10-14': -1.2146, '2020-10-15': 1.2295, '2020-10-16': 6.2753, '2020-10-19': 2.6667, '2020-10-20': 0.0, '2020-10-21': 0.7421, '2020-10-22': -2.0258, '2020-10-23': -0.188, '2020-10-26': -1.1299, '2020-10-27': -1.3333, '2020-10-28': 2.7027, '2020-10-29': -2.6316, '2020-10-30': -1.7375}; 3.日成交量（亿):{'2020-10-09': 244074.07, '2020-10-12': 227451.48, '2020-10-13': 161650.37, '2020-10-14': 113839.65, '2020-10-15': 300253.83, '2020-10-16': 800526.52, '2020-10-19': 748027.44, '2020-10-20': 386830.14, '2020-10-21': 460101.23, '2020-10-22': 293724.38, '2020-10-23': 224054.7, '2020-10-26': 229509.69, '2020-10-27': 231946.46, '2020-10-28': 284687.68, '2020-10-29': 236397.34, '2020-10-30': 248039.11}",
        "generated_question": "神火股份（000933）公司三季报显示业绩大幅改善，云南神火并表驱动增长，煤铝主业经营改善，新疆神火和泉店煤矿增利，同时原材料价格下降降低成本。集团计划未来六个月增持股份，显示对业绩增长的信心。基于近期市场数据，该股票下个月的最终收益预测为‘涨’，上涨概率为‘极大’。请问这一预测是如何得出的？",
        "trend_keywords": [
          "增加",
          "减少",
          "亏损"
        ],
        "year_keywords": [
          "2020",
          "2022",
          "2019",
          "2021"
        ],
        "term_keywords": [],
        "context_trend_score": 3,
        "context_year_score": 4,
        "context_term_score": 0,
        "question_trend_score": 0,
        "question_year_score": 0,
        "question_term_score": 0,
        "trend_score": 3,
        "year_score": 4,
        "term_score": 0,
        "total_score": 7,
        "context_score": 7,
        "diversity_score": 0.0
      }
    ],
    "year": [
      {
        "sample_id": "unknown",
        "summary": "神火股份（000933）公司三季报业绩大幅改善，扣非后净利润同比增长203%，主要得益于云南神火并表驱动增长。公司优化产业结构，煤铝主业经营改善明显，新疆神火、泉店煤矿增利显著，同时原材料价格下降进一步降低成本。云南神火完成并表后，集团计划在未来六个月内增持不超过1.5%的股份，显示出对未来业绩增长的信心。近期市场数据显示，股票价格波动较大，但整体趋势向上。预测结果显示，该股票下个月最终收益为‘涨’，上涨概率为‘极大’。",
        "content": "研报题目是:神火股份（000933）公司三季报点评报告：扣非后业绩同比大幅改善，集团增持彰显未来信心；目标价格是目标价格未公布，评分是7.0；研报摘要:神火股份 000933 事件 公司发布 2020 年三季报， 2020Q1 Q3 实现扣非后归母净利润 2 99 亿元，较 2019 年同期 调整前， 亏损 2 91 亿元 增加 5 91 亿元，增幅达 203 实现归母净利润 4 93 亿元，较 2019 年同期 调整前 减少 80 4 。2020Q3 单季业绩大幅改善，云南神火并表驱动未来成长2020 年前三季度公司归母净利同比降幅明显，主因 2019Q3 回收高家庄煤矿 24 6亿元转让款确认大额资产处置收益，抬高基数。扣非后来看， 2020Q3 单季扣非后归母净利润为 1 52 亿元，在 2019 年同期 0 42 亿元基础上增加 1 99 亿元， 且超过上半年扣非业绩总和， 公司近年来积极优化产业结构成效显著，煤铝主业经营均明显改善。 未来梁北矿扩产有序推进 云南神火预计 2021 年初完全通电后将贡献全年业绩。考虑到云南神火通电后盈利超预期，且公司权益比例提升，我们上调盈利预测，预计 2020 2021 2022 年归母净利润 7 3 0 5 12 8 2 9 15 9 3 1 亿 元 ， 同 比 45 8 75 4 23 8 EPS 为 0 38 0 02 0 67 0 15 0 83 0 16 元， 对应当前股价 PE 分别为 13 9x 7 9x 6 4x。 维持 买入 评级。煤、铝主业经营状况明显改善，新疆神火、泉店煤矿大幅增利受益原材料价格下降，新疆神火同比增利 3 亿元。 前三季度新疆神火实现利润7 75 亿元，同比增加 3 95 亿元，其中三季度实现 3 84 亿元，环比增加 1 88 亿元。氧化铝、阳极炭块价格下降致吨铝完全成本同比减少 760 元 吨。 煤价走强，泉店矿增利 0 63 亿元。 泉店矿是公司产能最大的在产煤矿，前三季度吨煤价格同比 73 7 元 吨，吨煤成本同比 23 3 元 吨。 本部氧化铝产能出清，汇源铝业关停业绩减亏 1 92 亿元。 公司于 2019 年底关停汇源铝业 80 万吨亏损产能，经营利润同比减亏 2 59 亿元。 总体来看，煤铝主业经营状况明显改善。云南神火完成并表满产在即， 集团增持股份彰显信心公司 9 月对云南神火完成并表，持股比例由 32 2 增至 43 4 ，权益增加将增厚项目业绩贡献。 一系列 45 万吨已于 9 月初完全通电， 年内可贡献约 30 万吨产量， 二系列 45 万吨预计 2021Q1 完全通电，可几乎贡献全年业绩。 煤炭方面，梁北矿技改扩产预计年底试运营，产能将新增 150 万吨。同时，集团拟在半年内增持不超过 1 5 股份，凸显了对公司未来业绩前景的信心与对投资价值的认可。风险提示 煤、铝价格下跌超预期 煤矿停减产风险 云南项目进展不及预期。同时，下面我提供的一份该股票的近期市场数据， 提示:我提供的数据一般是由三个字段组成，分别是每个对应日期的股票价格，涨跌幅，成交量数据。 数据如下: 1.该企业的近期数据如下:1.股票价格（元）:{'2020-10-09': 4.84, '2020-10-12': 4.98, '2020-10-13': 4.94, '2020-10-14': 4.88, '2020-10-15': 4.94, '2020-10-16': 5.25, '2020-10-19': 5.39, '2020-10-20': 5.39, '2020-10-21': 5.43, '2020-10-22': 5.32, '2020-10-23': 5.31, '2020-10-26': 5.25, '2020-10-27': 5.18, '2020-10-28': 5.32, '2020-10-29': 5.18, '2020-10-30': 5.09}; 2.日涨跌幅（%）:{'2020-10-09': 4.7619, '2020-10-12': 2.8926, '2020-10-13': -0.8032, '2020-10-14': -1.2146, '2020-10-15': 1.2295, '2020-10-16': 6.2753, '2020-10-19': 2.6667, '2020-10-20': 0.0, '2020-10-21': 0.7421, '2020-10-22': -2.0258, '2020-10-23': -0.188, '2020-10-26': -1.1299, '2020-10-27': -1.3333, '2020-10-28': 2.7027, '2020-10-29': -2.6316, '2020-10-30': -1.7375}; 3.日成交量（亿):{'2020-10-09': 244074.07, '2020-10-12': 227451.48, '2020-10-13': 161650.37, '2020-10-14': 113839.65, '2020-10-15': 300253.83, '2020-10-16': 800526.52, '2020-10-19': 748027.44, '2020-10-20': 386830.14, '2020-10-21': 460101.23, '2020-10-22': 293724.38, '2020-10-23': 224054.7, '2020-10-26': 229509.69, '2020-10-27': 231946.46, '2020-10-28': 284687.68, '2020-10-29': 236397.34, '2020-10-30': 248039.11}",
        "generated_question": "神火股份（000933）公司三季报显示业绩大幅改善，云南神火并表驱动增长，煤铝主业经营改善，新疆神火和泉店煤矿增利，同时原材料价格下降降低成本。集团计划未来六个月增持股份，显示对业绩增长的信心。基于近期市场数据，该股票下个月的最终收益预测为‘涨’，上涨概率为‘极大’。请问这一预测是如何得出的？",
        "trend_keywords": [
          "增加",
          "减少",
          "亏损"
        ],
        "year_keywords": [
          "2020",
          "2022",
          "2019",
          "2021"
        ],
        "term_keywords": [],
        "context_trend_score": 3,
        "context_year_score": 4,
        "context_term_score": 0,
        "question_trend_score": 0,
        "question_year_score": 0,
        "question_term_score": 0,
        "trend_score": 3,
        "year_score": 4,
        "term_score": 0,
        "total_score": 7,
        "context_score": 7,
        "diversity_score": 0.0
      },
      {
        "sample_id": "unknown",
        "summary": "一汽解放于2006年9月22日的股票分析数据显示，其股息率为6.4309%。",
        "content": "{'TS股票代码': '000800.SZ', '交易日': '2006-09-22', '换手率（%）': 0.6302, '市盈率（总市值/净利润， 亏损的PE为空）': 14.9916, '市销率（TTM）': 0.4857, '股息率（TTM）（%）': 6.4309, '总股本 （万股）': 162750.0, '流通股本 （万股）': 72615.5794, '总市值 （万元）': 506152.5}。",
        "generated_question": "一汽解放(000800.SZ)于2006年9月22日的股息率是多少？",
        "trend_keywords": [],
        "year_keywords": [
          "2006"
        ],
        "term_keywords": [
          "市盈率",
          "换手率",
          "市销率",
          "净利润"
        ],
        "context_trend_score": 0,
        "context_year_score": 1,
        "context_term_score": 4,
        "question_trend_score": 0,
        "question_year_score": 0,
        "question_term_score": 0,
        "trend_score": 0,
        "year_score": 1,
        "term_score": 4,
        "total_score": 5,
        "context_score": 5,
        "diversity_score": 0.0
      },
      {
        "sample_id": "unknown",
        "summary": "阳光电源在2023年4月24日的股票数据包括：股票代码300274.SZ，当日收盘价103.4元，量比1.26，市盈率97.0291，市销率6.3625，股息率0.1064%，自由流通股本96122.9317万。其中，市销率是6.3625。",
        "content": "{'TS股票代码': '300274.SZ', '交易日': '2023-04-24', '当日收盘价': 103.4, '量比': 1.26, '市盈率（总市值/净利润， 亏损的PE为空）': 97.0291, '市销率': 6.3625, '市销率（TTM）': 4.9559, '股息率 （%）': 0.1064, '股息率（TTM）（%）': 0.1064, '自由流通股本 （万）': 96122.9317}。",
        "generated_question": "阳光电源在2023年4月24日的市销率是多少？",
        "trend_keywords": [],
        "year_keywords": [
          "2023"
        ],
        "term_keywords": [
          "市盈率",
          "市销率",
          "净利润"
        ],
        "context_trend_score": 0,
        "context_year_score": 1,
        "context_term_score": 3,
        "question_trend_score": 0,
        "question_year_score": 0,
        "question_term_score": 0,
        "trend_score": 0,
        "year_score": 1,
        "term_score": 3,
        "total_score": 4,
        "context_score": 4,
        "diversity_score": 0.0
      },
      {
        "sample_id": "unknown",
        "summary": "崇达技术的业务结构持续优化，投资扩产稳步进行，特别是在国内市场的拓展和5G业务方面表现突出。公司通过深化大客户战略，优化市场结构，成功引入更多战略客户，如英特尔、三星电子等。研发投入增加，特别是在5G相关产品的开发上取得了显著成果。各工厂的产销情况良好，产能利用有效提升。公司预计随着5G通讯网络的加速建设，将享受到5G带来的红利。基于此，给予崇达技术买入A评级。",
        "content": "研报题目是:崇达技术（002815）：业务结构持续优化，投资扩产稳步进行；目标价格是目标价格未公布，评分是7.0；研报摘要:崇达技术 002815 事件 2020 年 4 月 30 日，公司发布 2019 年年报和 2020 年一季报。2019 年公司实现营业收入 37 27 亿元，同比上升 1 95 归属于上市公司股东净利润 5 26 亿元，同比下降 6 16 扣非后归母净利润 4 97 亿元，同比下降 7 17 。2020 年 Q1 公司实现总收 9 32 亿元，同比上升2 94 归属于上市公司股东净利润 1 26 亿元，同比上升 1 61 扣非后归母净利润 1 05 亿元，同比下降 11 25 。市场结构持续优化，深入推进大客户战略。公司近几年来不断加大国内市场的开拓力度， 2014 2019 年期间，中国大陆销售占比由 19 71 提升至 27 57 ，已成为公司最大的销售区域，这有利于公司对冲国际贸易摩擦的波动风险。2019 年国内大客户的批量订单逐步释放，国内市场收入继续保持了较快增长，公司深入推动行业大客户销售策略，加强与世界 500 强及各行业领头企业的合作，根据公司公告，5G 客户方面，公司合作的主要客户有中兴、烽火通信、普天、康普 CommScope 、高意 II VI 、Calix、博通 Broadcom 、旭创科技等，又持续引入了英特尔 Intel 、三星电子 Samsung 、住友电工 SUMITOMO ELECTRIC 、立讯精密等战略客户。顺应 5G 通讯趋势，研发投入大幅增加。2019 年为中国 5G 建设和商用元年，公司关于 5G 的研发投入大幅增加，其中研发费用同比增长 28 20 ，公司成功实现了应用于超级计算机和 5G 基站的高密度高速多层板的大批量生产，同时公司也继续加大 5G 相关产品的研发投入，尤其在通信传输网、核心网、数据中心等方面的应用领域。公司2020 年 4 月在全景网互动平台表示， 5G 方面的订单增长较快。 我们预计随着 5G 通讯网络的加速建设和后续应用产业的快速增长，公司有望享受 5G 红利。各工厂产销情况良好，投资扩产稳步推进。2019 年，公司生产和销售 PCB 的面积分别为 292 89 万平方米、292 91 万平米，产销率达到100 01 。深圳崇达在 2019 年下半年成功导入中兴，切入 5G 快车道，为未来业绩的保障打下坚实基础。江门崇达二厂是 IPO 募投项目， 2019 年销量受制于工业类 HDI 景气度的下滑， 产能未能得到完全释放，为提升产能利用率，公司已加快导入消费类 HDI 产品以及其它高端 PCB产品。大连崇达主要生产 2 6 层的多品种小批量 PCB 产品，产能利用率较高， 根据公告， 二期目前正在筹建中，预计未来将继续提升产能。根据公告，公司已经布局持有三德冠 40 股权、普诺威 40 股权，将产品扩展至 FPC、 IC 载板等领域， 实现了 PCB 全系列产品的覆盖。全产品线覆盖的一站式产品能够满足客户不同类型产品的需求，从而增强公司产品的竞争力。投资建议 我们预计公司 2020 2021 年的营业收入分别为 46 28 亿元、56 39 亿元、，归属上市公司股东的净利润分别为 6 65 亿元、8 63 亿元，给予买入 A 评级。风险提示 宏观经济及下游行业的周期性波动风险，原材料价格波动风险，汇率波动风险同时，下面我提供的一份该股票的近期市场数据， 提示:我提供的数据一般是由三个字段组成，分别是每个对应日期的股票价格，涨跌幅，成交量数据。 数据如下: 1.该企业的近期数据如下:1.股票价格（元）:{'2020-05-06': 18.24, '2020-05-07': 19.22, '2020-05-08': 19.35, '2020-05-11': 19.41, '2020-05-12': 19.34, '2020-05-13': 19.33, '2020-05-14': 19.06, '2020-05-15': 19.5, '2020-05-18': 18.65, '2020-05-19': 18.84, '2020-05-20': 18.54, '2020-05-21': 18.33, '2020-05-22': 18.03, '2020-05-25': 17.74, '2020-05-26': 18.31, '2020-05-27': 17.95, '2020-05-28': 18.25, '2020-05-29': 17.74}; 2.日涨跌幅（%）:{'2020-05-06': 2.8765, '2020-05-07': 5.3728, '2020-05-08': 0.6764, '2020-05-11': 0.3101, '2020-05-12': -0.3606, '2020-05-13': -0.0517, '2020-05-14': -1.3968, '2020-05-15': 2.3085, '2020-05-18': -4.359, '2020-05-19': 1.0188, '2020-05-20': -1.5924, '2020-05-21': -1.1327, '2020-05-22': -1.6367, '2020-05-25': -1.6084, '2020-05-26': 3.2131, '2020-05-27': -1.9661, '2020-05-28': 1.6713, '2020-05-29': -2.7945}; 3.日成交量（亿):{'2020-05-06': 179410.21, '2020-05-07': 307652.72, '2020-05-08': 198256.97, '2020-05-11': 129421.63, '2020-05-12': 130585.59, '2020-05-13': 75055.37, '2020-05-14': 98567.03, '2020-05-15': 184932.83, '2020-05-18': 173976.61, '2020-05-19': 128475.73, '2020-05-20': 110426.06, '2020-05-21': 102184.33, '2020-05-22': 99041.33, '2020-05-25': 93999.36, '2020-05-26': 79172.65, '2020-05-27': 121161.48, '2020-05-28': 120732.9, '2020-05-29': 109966.07}",
        "generated_question": "崇达技术（002815）在最近的研究报告中，其业务结构和投资扩产状况如何？",
        "trend_keywords": [],
        "year_keywords": [
          "2020",
          "2021",
          "2019",
          "2014"
        ],
        "term_keywords": [],
        "context_trend_score": 0,
        "context_year_score": 4,
        "context_term_score": 0,
        "question_trend_score": 0,
        "question_year_score": 0,
        "question_term_score": 0,
        "trend_score": 0,
        "year_score": 4,
        "term_score": 0,
        "total_score": 4,
        "context_score": 4,
        "diversity_score": 0.0
      },
      {
        "sample_id": "unknown",
        "summary": "报告指出创维数字（000810）短期内面临需求承压和收入下滑的压力，特别是智能终端业务在国内市场的表现不佳，但海外市场需求有所增长。报告下调了公司2020-2022年的EPS预测，并给出了公司的买入评级。短期内，收入及盈利承压，但报告认为中长期网络融合发展的趋势对公司有利。报告建议给予公司2021年18倍PE的目标价格。",
        "content": "研报题目是:创维数字（000810）：短期需求承压，收入结构影响利润；目标价格是11.16，评分是7.0；研报摘要:创维数字 000810 2020Q3 收入 归母净利同比 6 77 57 23 ，维持 买入 评级公司披露 2020 年三季报，2020Q1 Q3 公司实现营业总收入 59 37 亿元，同比 5 57 ，归母净利 2 81 亿元，同比 42 90 ，其中，2020Q3 营收同比 6 77 ，归母净利同比 57 23 。公司国内智能终端需求景气度依然偏低，海外需求虽有增长，但整体依然面临收入下滑压力。中长期内，我们看好公司继续发掘网络融合需求，拓展宽带接入设备收入空间，同时公司在专业显示领域合作稳定，受益于 5G 换机需求。 我们下调公司 2020 2022年 EPS 为 0 53、0 62、0 72 元，维持 买入 评级。2020Q3 收入仍同比下滑，智能终端业务或依然有压力2020Q3 收入同比 6 77 ，考虑到国内市场传统机顶盒需求减弱，公司主要与广电运营商及三大运营商合作，需求偏弱的背景下，智能终端业务内销或依然承压，相对而言，海外市场疫情影响明显，电视观看需求增长，或依然带来出口增长，综合内外销情况，我们预计智能终端收入依然有所下滑。而公司专业显示业务主要提供中小尺寸模组、车载显示等产品，受益于 5G 手机换机潮，我们预计专业显示业务收入延续 H1 表现，继续同比增长。2020Q3 产品毛利率同比大幅下滑受低毛利业务增长较快拖累，公司 2020Q1 Q3 毛利率 18 65 ，同比 3 77pct，其中 2020Q3 毛利率同比 5 50pct。 虽然原材料价格同比有所优化 2020 年 1 9 月，Wind 数据显示 DDR3 2Gb、DDR3 4Gb 均价分别同比 8 6 、 11 8 。 ，但公司低毛利专业显示业务收入占比或有提升，整体影响公司毛利率水平。2020Q3 期间费用率同比明显提升，主要受研发及财务费用率影响202020Q1 Q3 公司整体期间费用率同比 1 24pct，其中， Q3 同比 1 16pct，拆分来看，2020Q3 销售费用率同比 0 19pct、管理费用率同比 0 06pct、研发费用率同比 0 74pct、财务费用率 0 63pct 人民币汇率影响，产生较大汇兑损失 。2020Q3 经营活动现金流净额同比 8 96 。短期收入及盈利承压，看好中长期网络融合发展考虑到国内用户需求景气度依然偏低，同时低毛利率 ToB 业务占比提升，我们下调了营收、毛利率以及归母净利润，调整了部分费用率指标，预测公司 2020 2022 年 EPS 为 0 53、0 62、0 72 元 前值 0 72、0 83、0 92元 。 截至 2020 年 10 月 26 日， 根据 Wind 一致预期，行业可比公司 2021年平均 PE 为 14x， 短期公司收入及盈利增长虽有压力，但公司为网络智能终端优势企业，具备丰富的运营商渠道资源，仍受益于国内和海外超高清及网络融合产品的更新提速，中长期收入仍有增长空间。认可给予公司 2021年 18x PE，对应目标价格 11 16 元 前值 15 84 元 ，维持 买入 评级。风险提示 政策不确定性 行业竞争加剧 原材料成本波动 疫情蔓延。同时，下面我提供的一份该股票的近期市场数据， 提示:我提供的数据一般是由三个字段组成，分别是每个对应日期的股票价格，涨跌幅，成交量数据。 数据如下: 1.该企业的近期数据如下:1.股票价格（元）:{'2020-10-09': 9.88, '2020-10-12': 10.23, '2020-10-13': 10.19, '2020-10-14': 9.99, '2020-10-15': 9.99, '2020-10-16': 9.84, '2020-10-19': 9.88, '2020-10-20': 10.18, '2020-10-21': 10.07, '2020-10-22': 10.19, '2020-10-23': 10.09, '2020-10-26': 10.12, '2020-10-27': 9.59, '2020-10-28': 9.09, '2020-10-29': 9.02, '2020-10-30': 8.7}; 2.日涨跌幅（%）:{'2020-10-09': 2.9167, '2020-10-12': 3.5425, '2020-10-13': -0.391, '2020-10-14': -1.9627, '2020-10-15': 0.0, '2020-10-16': -1.5015, '2020-10-19': 0.4065, '2020-10-20': 3.0364, '2020-10-21': -1.0806, '2020-10-22': 1.1917, '2020-10-23': -0.9814, '2020-10-26': 0.2973, '2020-10-27': -5.2372, '2020-10-28': -5.2138, '2020-10-29': -0.7701, '2020-10-30': -3.5477}; 3.日成交量（亿):{'2020-10-09': 38623.4, '2020-10-12': 60284.49, '2020-10-13': 38553.26, '2020-10-14': 48751.0, '2020-10-15': 38277.99, '2020-10-16': 43244.48, '2020-10-19': 47258.99, '2020-10-20': 81618.35, '2020-10-21': 48964.42, '2020-10-22': 57686.05, '2020-10-23': 42811.34, '2020-10-26': 30793.35, '2020-10-27': 130922.99, '2020-10-28': 121724.15, '2020-10-29': 78695.4, '2020-10-30': 71291.43}",
        "generated_question": "关于创维数字（000810）的最新研报显示了哪些信息？",
        "trend_keywords": [],
        "year_keywords": [
          "2020",
          "2022",
          "2021"
        ],
        "term_keywords": [
          "收入"
        ],
        "context_trend_score": 0,
        "context_year_score": 3,
        "context_term_score": 1,
        "question_trend_score": 0,
        "question_year_score": 0,
        "question_term_score": 0,
        "trend_score": 0,
        "year_score": 3,
        "term_score": 1,
        "total_score": 4,
        "context_score": 4,
        "diversity_score": 0.0
      },
      {
        "sample_id": "unknown",
        "summary": "这份利润表数据显示了分众传媒在2013年12月31日的财务状况，包括营业收入、营业成本、财务费用等关键指标，以及所得税费用为19,182,472.01。",
        "content": "{'TS代码': '002027.SZ', '实际公告日期': Timestamp('2014-04-28 00:00:00'), '公司类型(1一般工商业2银行3保险4证券)': '1', '营业收入': 255848675.51, '减:营业成本': 292550533.16, '减:营业税金及附加': 110342.33, '减:财务费用': 788526.05, '利润总额': -66267573.79, '所得税费用': 19182472.01, '归属于少数股东的综合收益总额': '-1157120.46', '交易日': '2013-12-31'}。",
        "generated_question": "分众传媒在2013年的所得税费用是多少？",
        "trend_keywords": [],
        "year_keywords": [
          "2013",
          "2014"
        ],
        "term_keywords": [
          "营业收入"
        ],
        "context_trend_score": 0,
        "context_year_score": 2,
        "context_term_score": 1,
        "question_trend_score": 0,
        "question_year_score": 0,
        "question_term_score": 0,
        "trend_score": 0,
        "year_score": 2,
        "term_score": 1,
        "total_score": 3,
        "context_score": 3,
        "diversity_score": 0.0
      },
      {
        "sample_id": "unknown",
        "summary": "立讯精密于2021年6月30日发布的利润表数据显示，其营业总成本为256,325,427,354.55元，其中减去营业成本后的金额为228,699,652,965.8元，资产减值损失为-4,048,920.76元，最终营业利润为1,998,326,683.29元。",
        "content": "{'TS代码': '002475.SZ', '报告期': '20210630', '营业总成本': 25632542735.45, '减:营业成本': 22869965296.58, '减:资产减值损失': '-40489207.65', '营业利润': 1998326683.29, '减:营业外支出': 32721299.46, '净利润(含少数股东损益)': 2004305455.92, '其他综合收益': '28952514.81', '更新标识': '0', '交易日': '2021-06-30'}。",
        "generated_question": "立讯精密（002475.SZ）于2021年6月30日的营业利润是多少？",
        "trend_keywords": [],
        "year_keywords": [
          "2021"
        ],
        "term_keywords": [
          "营业利润",
          "净利润"
        ],
        "context_trend_score": 0,
        "context_year_score": 1,
        "context_term_score": 2,
        "question_trend_score": 0,
        "question_year_score": 0,
        "question_term_score": 0,
        "trend_score": 0,
        "year_score": 1,
        "term_score": 2,
        "total_score": 3,
        "context_score": 3,
        "diversity_score": 0.0
      },
      {
        "sample_id": "unknown",
        "summary": "抚顺特钢2022年三季报显示，尽管高温合金等高端产品保持增长，但整体销量下滑影响了Q3业绩。原料成本压力有所缓解，但能源成本上升及民品需求不佳导致产品售价下降，毛利率环比下滑。公司持续加码技改项目，高温合金未来贡献潜力大。近期股票价格波动较大，日涨跌幅和成交量也呈现出不稳定趋势。",
        "content": "研报题目是:抚顺特钢（600399）2022年三季报点评：销量下滑拖累Q3业绩，高温合金等高端产品稳步增长；目标价格是目标价格未公布，评分是5.0；研报摘要:抚顺特钢 600399 事件概述 10 月 28 日， 公司发布 2022 三季度报 2022 前三季度，公司实现营收57 37 亿元，同比增长 3 归母净利润 2 99 亿元，同比减少 56 4 扣非归母净利 2 53亿元，同比减少 59 9 。 2022Q3，公司实现营收 19 22 亿元，同比增长 6 8 、环比减少 3 6 归母净利润 1 16 亿元，同比减少 54 4 、环比增长 18 3 扣非归母净利 1 02亿元，同比减少 54 、环比增长 18 9 。业绩低于预期。点评 销量下滑拖累 Q3 业绩 量 Q3 高温合金，不锈钢销量维持增长。 公司前三季度钢材销量 34 54 万吨，同比 17 35 ，结构上看， 高温合金销量 0 55 万吨，同比 20 45 ，不锈钢销量 6 81 万吨，同比 31 45 ，其他钢材品种销量负增长。 分季度看， 22Q3 公司钢材销量 10 38万吨，同比 11 43 ，环比 18 97 ，其中高温合金、 不锈钢销量维持正增长，高温合金销量环比 5 56 ，不锈钢销量环比 9 22 。 整体看，公司高端产品需求旺盛，但合金钢等钢种需求不佳，导致销量下滑。 价 Q3 原料成本压力缓解， 但由于能源成本上升，产品售价下行， 毛利率环比 0 87pct。 三季度原料成本压力环比缓解，其中镍价环比 16 22 ， 钴价环比 29 33 ，废钢价格环比 19 56 ， 但由于能源成本上升以及民品需求不佳导致部分产品价格走弱， 公司 Q3 毛利率环比 0 87pct， 同比 10 87pct， 至 13 12 。 三费 Q3 三费大幅下滑。 Q3 公司三费 5152 83 万元， 同比 35 73 ，环比 28 92 ，其中管理费用同比 23 55 ， 销售费用同比 8 29 ，财务费用同比 80 52 。 年内现汇回款比例增加， 经营活动现金流好转，公司 Q3 利息收入同比增加 2824 万元， 导致财务费用下滑。未来核心看点 持续加码技改项目，产品结构进一步向高端化转变 高温合金未来贡献可期。 2021 年公司高温合金毛利率高达 42 65 ，是公司唯一毛利率上升的业务， 22H1 公司高温合金业务稳步增长，占营收比重同比提升 2 4pct，至 20 18 。军用等领域需求增长带动高温合金销量稳步提升，增厚公司业绩。 前期规划的新增 16 68 万吨产能项目稳步推进中。 公司前期规划的多个技改项目在途，新增 16 68 万吨产能稳步推进中，产品结构有望进一步向高端化转变。 加码技改项目，未来 2 年公司产能有望加速扩张。 为进一步提高公司产品交付能力及产品质量，公司继续加码投资建设相关技术改造项目，未来 2 年将会增加相关产能25 万吨以上，有望持续提升公司国内外市场竞争力和行业影响力。投资建议 公司重点发展军工等领域产品，随着多个技改项目逐步投产，产品结构有望进一步优化。我们预计公司 2022 2024 年归母净利润依次 4 67 9 73 12 92 亿元，对应现价， 2022 2024 年 PE 依次为 72 34 26 倍，维持公司 谨慎推荐 评级。风险提示 项目不及预期 技术研发风险 下游需求不及预期等。同时，下面我提供的一份该股票的近期市场数据， 提示:我提供的数据一般是由三个字段组成，分别是每个对应日期的股票价格，涨跌幅，成交量数据。 数据如下: 1.该企业的近期数据如下:1.股票价格（元）:{'2022-11-01': 17.91, '2022-11-02': 17.5, '2022-11-03': 17.8, '2022-11-04': 18.06, '2022-11-07': 17.65, '2022-11-08': 17.71, '2022-11-09': 17.48, '2022-11-10': 16.99, '2022-11-11': 17.0, '2022-11-14': 16.55, '2022-11-15': 16.71, '2022-11-16': 16.5, '2022-11-17': 16.45, '2022-11-18': 16.05, '2022-11-21': 16.35, '2022-11-22': 16.14, '2022-11-23': 16.02, '2022-11-24': 15.82, '2022-11-25': 15.21, '2022-11-28': 15.33, '2022-11-29': 15.0, '2022-11-30': 15.07}; 2.日涨跌幅（%）:{'2022-11-01': -1.4851, '2022-11-02': -2.2892, '2022-11-03': 1.7143, '2022-11-04': 1.4607, '2022-11-07': -2.2702, '2022-11-08': 0.3399, '2022-11-09': -1.2987, '2022-11-10': -2.8032, '2022-11-11': 0.0589, '2022-11-14': -2.6471, '2022-11-15': 0.9668, '2022-11-16': -1.2567, '2022-11-17': -0.303, '2022-11-18': -2.4316, '2022-11-21': 1.8692, '2022-11-22': -1.2844, '2022-11-23': -0.7435, '2022-11-24': -1.2484, '2022-11-25': -3.8559, '2022-11-28': 0.789, '2022-11-29': -2.1526, '2022-11-30': 0.4667}; 3.日成交量（亿):{'2022-11-01': 281977.74, '2022-11-02': 394799.29, '2022-11-03': 239628.03, '2022-11-04': 242196.1, '2022-11-07': 228725.08, '2022-11-08': 111742.2, '2022-11-09': 254500.95, '2022-11-10': 144051.8, '2022-11-11': 142074.24, '2022-11-14': 192031.2, '2022-11-15': 130626.56, '2022-11-16': 131693.74, '2022-11-17': 166466.76, '2022-11-18': 137286.44, '2022-11-21': 175365.74, '2022-11-22': 132679.05, '2022-11-23': 153729.86, '2022-11-24': 133193.02, '2022-11-25': 268199.11, '2022-11-28': 165975.0, '2022-11-29': 250907.5, '2022-11-30': 195001.64}",
        "generated_question": "抚顺特钢（600399）2022年三季报主要显示了哪些业绩变化？",
        "trend_keywords": [],
        "year_keywords": [
          "2024",
          "2022",
          "2021"
        ],
        "term_keywords": [],
        "context_trend_score": 0,
        "context_year_score": 3,
        "context_term_score": 0,
        "question_trend_score": 0,
        "question_year_score": 0,
        "question_term_score": 0,
        "trend_score": 0,
        "year_score": 3,
        "term_score": 0,
        "total_score": 3,
        "context_score": 3,
        "diversity_score": 0.0
      },
      {
        "sample_id": "unknown",
        "summary": "云南白药公司在2002年3月31日的报告期内，净利润（含少数股东损益）为19,838,873.03元。",
        "content": "{'TS代码': '000538.SZ', '实际公告日期': Timestamp('2002-04-18 00:00:00'), '报告期': '20020331', '公司类型(1一般工商业2银行3保险4证券)': '1', '营业总收入': 226799360.57, '营业总成本': 203380938.69, '营业利润': 23870124.3, '加:营业外收入': 54137.89, '净利润(含少数股东损益)': 19838873.03, '更新标识': '0', '交易日': '2002-03-31'}。",
        "generated_question": "云南白药公司在2002年3月31日的报告期内，净利润（含少数股东损益）是多少？",
        "trend_keywords": [],
        "year_keywords": [
          "2002"
        ],
        "term_keywords": [
          "营业利润",
          "净利润"
        ],
        "context_trend_score": 0,
        "context_year_score": 1,
        "context_term_score": 2,
        "question_trend_score": 0,
        "question_year_score": 0,
        "question_term_score": 1,
        "trend_score": 0,
        "year_score": 1,
        "term_score": 2,
        "total_score": 3,
        "context_score": 3,
        "diversity_score": 0.0
      },
      {
        "sample_id": "unknown",
        "summary": "恩捷股份（002812）的2021年半年报显示，公司营收和净利润均大幅增长，湿法隔膜出货量稳定增长，市占率优势显著。产能扩张积极，计划未来三年每年新增产线25-30-40条，以提高市场占有率。在线涂覆和铝塑膜业务也在积极推进。预计2021-2023年归母净利润分别为25.72、44.49、64.49亿元，同比增长130.6%、72.9%、45.0%，维持买入评级。",
        "content": "研报题目是:恩捷股份（002812）：锂电上游最强环节，产能扩张积极；目标价格是目标价格未公布，评分是7.0；研报摘要:核心结论事件 公司发布2021年半年报，上半年实现营业收入33 94亿元，同比增长135 6 ，实现归母净利润10 5亿元，同比增长226 8 。单季度看，21Q2公司实现营业收入19 51亿元，同比增长119 7 ，环比增长35 2 实现归母净利润6 18亿元，同比增长237 5 ，环比增长43 0 。业绩符合预期。湿法隔膜出货量稳定增长，恩捷市占率优势巨大。21H1恩捷湿法隔膜出货量超12亿平，市场占有率55 4 ，同比提升22 5pct。公司市占率快速提升，一方面受益于苏州捷力、纽米科技并表的积极影响，另一方面，公司通过提高车速、拓展幅宽，有效提升生产效率。设备厂积极配合公司快速扩张。公司今年底预计有效产线60条，在日本制钢所的全力配合下，公司未来三年产线投放进度分别为每年25 30 40条，将有效提高市占率。同时，公司为缓解设备供应短缺而积极开展关键设备研发，预计明年下半年部分自研设备投入使用，在数据收集、大数据分析方面会有明显提升，显著提高产品收率、降低成本。在线涂覆进展顺利，铝塑膜业务积极推进。公司已在江西、无锡和珠海启动5条在线涂覆产线，预计年底投产11条。铝塑膜规划产能江西1 5亿平 常州2 6亿平，为全球最大。目前3C类铝塑膜已有出货，动力类均已进入认证流程。投资建议 预计公司2021 2022 2023年归母净利润为25 72 44 49 64 49亿元，同比增长130 6 72 9 45 0 ，对应EPS为2 88 4 99 7 23元，维持 买入 评级。风险提示 电动车销量不及预期， 产能扩张不及预期，价格下降超预期。同时，下面我提供的一份该股票的近期市场数据， 提示:我提供的数据一般是由三个字段组成，分别是每个对应日期的股票价格，涨跌幅，成交量数据。 数据如下: 1.该企业的近期数据如下:1.股票价格（元）:{'2021-08-02': 252.0, '2021-08-03': 255.95, '2021-08-04': 281.55, '2021-08-05': 290.88, '2021-08-06': 290.02, '2021-08-09': 287.2, '2021-08-10': 260.17, '2021-08-11': 264.0, '2021-08-12': 259.26, '2021-08-13': 259.0, '2021-08-16': 241.44, '2021-08-17': 234.99, '2021-08-18': 241.9, '2021-08-19': 258.3, '2021-08-20': 256.0, '2021-08-23': 265.76, '2021-08-24': 278.0, '2021-08-25': 276.1, '2021-08-26': 283.63, '2021-08-27': 279.0, '2021-08-30': 285.0, '2021-08-31': 282.4}; 2.日涨跌幅（%）:{'2021-08-02': 1.5924, '2021-08-03': 1.5675, '2021-08-04': 10.002, '2021-08-05': 3.3138, '2021-08-06': -0.2957, '2021-08-09': -0.9723, '2021-08-10': -9.4116, '2021-08-11': 1.4721, '2021-08-12': -1.7955, '2021-08-13': -0.1003, '2021-08-16': -6.7799, '2021-08-17': -2.6715, '2021-08-18': 2.9406, '2021-08-19': 6.7797, '2021-08-20': -0.8904, '2021-08-23': 3.8125, '2021-08-24': 4.6057, '2021-08-25': -0.6835, '2021-08-26': 2.7273, '2021-08-27': -1.6324, '2021-08-30': 2.1505, '2021-08-31': -0.9123}; 3.日成交量（亿):{'2021-08-02': 121059.42, '2021-08-03': 80335.97, '2021-08-04': 71475.41, '2021-08-05': 120372.45, '2021-08-06': 108204.73, '2021-08-09': 85135.75, '2021-08-10': 126530.15, '2021-08-11': 103193.14, '2021-08-12': 74691.95, '2021-08-13': 84938.15, '2021-08-16': 138384.17, '2021-08-17': 117148.95, '2021-08-18': 69774.05, '2021-08-19': 95864.83, '2021-08-20': 79736.51, '2021-08-23': 80182.58, '2021-08-24': 74282.81, '2021-08-25': 78555.55, '2021-08-26': 79395.23, '2021-08-27': 67013.05, '2021-08-30': 80421.32, '2021-08-31': 53420.17}",
        "generated_question": "恩捷股份（002812）在2021年半年报中表现出哪些业绩亮点？",
        "trend_keywords": [],
        "year_keywords": [
          "2022",
          "2021"
        ],
        "term_keywords": [],
        "context_trend_score": 0,
        "context_year_score": 2,
        "context_term_score": 0,
        "question_trend_score": 0,
        "question_year_score": 0,
        "question_term_score": 0,
        "trend_score": 0,
        "year_score": 2,
        "term_score": 0,
        "total_score": 2,
        "context_score": 2,
        "diversity_score": 0.0
      },
      {
        "sample_id": "unknown",
        "summary": "双汇发展（000895）2020年报显示，公司主业保持平稳增长，尽管受到屠宰业务拖累，利润端增速放缓。全年收入、利润稳定增长，主要受猪价高位影响。生鲜产品受高猪价影响增速较快，包装肉制品业务保持稳健增长。渠道分析显示，经销渠道为主要收入来源，但毛利率相对较低。进口肉使用量增加，有效控制成本。2020年销售毛利率为17.26%，期间费用率为5.66%，其中销售费用率3.60%。报告还提供了该股票近期市场数据，显示价格波动，涨跌幅情况以及成交量变化。",
        "content": "研报题目是:双汇发展（000895）2020年报点评：主业保持平稳增长，屠宰业务拖累利润端增速；目标价格是目标价格未公布，评分是5.0；研报摘要:事件概述3月30日，双汇发展公布2020 年年报，报告期内公司实现营收739 35 亿元，同比 22 51 实现归母净利润62 56 亿元同比 15 04 ，基本EPS为 1 86 元公司拟每10 股派发现金红利 1 68 元 含税 。二、分析与判断2020业绩保持稳健增长，毛利率小幅下滑地系利润端增速2020年公司实现营收 归母净利润739 35 62 56 亿元，同比分别 22 51 15 04 合Q4单季度实现营收 归母净利润18171 1317亿元，同比分别 0 99 11 86 。总体看，公司全年收入、利润端均保持稳健增长。其中猪价维持相对高位是届率业务收入增速较高的主要原因，但是生猪出栏量仍处于恢复期，导致屋率业务开工丰仍略有不足，毛利率同比小临下滑，拖累利润端增速。分产品看，公司包装肉制品 生鲜产品分别实现营收 280 98 482 67 亿元，同比分别 11 66 23 44 合H2分别实现营收140 98 243 62 亿元，同比分别 6 00 1 25 。生鲜产品受猪价较高影响，同比增速较快，包装肉制品业务保持稳健增长。分销量看 公司全年分别销售生鲜产品 包装肉制品 禽产品138 07 157 73 8 12万吨 同比分别 7 02 1 13 38 80 。生产品 包装肉制品分别实现销售单价34959 17814元 吨，同比分别 32 76 12 94 公司生鲜产品受展事量下降影响销售量有所下滑，包装肉制品业务实现量价齐升。分渠道看，公司全年经销 直销渠道分别实现收入 607 92 130 70 亿元，同比分别 15 20 73 38 分别实现毛利率19 50 6 86 ，同比分别 1 17ppt 1 2lppt。经销渠道仍是主要收入来源 直镇梁道增长较快，但毛利丰相对较低。关联交易方面，公司全年从国外采购进口肉、辅料等原材料共计160 29 亿元，同比 208 33 合 Q4 单季度采购58 22 亿元，同比 218 81 。公司进口肉使用量同比大幅增加，有效控制包装肉制品的成本。率业务地系毛利率，肉制品动销顺畅降任镇售费用率2020 年公司销售毛利率为 17 26 ，网比 1 53p Q4 为 16 36 ，比 0 86pp ，原别实现毛利率30 54 7 17 ，同比分别 2 09ppt 2 05ppt。2020 年期间费用率为5 66 ，同比1 30ppt Q4为6 31 ，同比 0 43ppt 。其中销售费用率为3 60 ，同比 0 89ppt Q4为3 77 ，同比 0 38pp ，原因是新收入准导致运杂费计入成本。管理费用车为1 88 ，网比 0 28 04为2 30 ，同比0 05ppt 。研发费用率为0 13 ，比 0 024为0 17 ，比 0 00p 。财务费费用率为0 04 ，同比 0 12ppt Q4为0 06 ，问比 0 09pp ，原是报告期内公司定期存款结息较同期增加，且汇兑损失较同期下降。同时，下面我提供的一份该股票的近期市场数据， 提示:我提供的数据一般是由三个字段组成，分别是每个对应日期的股票价格，涨跌幅，成交量数据。 数据如下: 1.该企业的近期数据如下:1.股票价格（元）:{'2021-03-01': 46.64, '2021-03-02': 46.05, '2021-03-03': 46.86, '2021-03-04': 45.59, '2021-03-05': 45.1, '2021-03-08': 43.55, '2021-03-09': 41.7, '2021-03-10': 40.88, '2021-03-11': 41.58, '2021-03-12': 41.17, '2021-03-15': 39.8, '2021-03-16': 40.67, '2021-03-17': 41.6, '2021-03-18': 41.09, '2021-03-19': 40.47, '2021-03-22': 40.81, '2021-03-23': 41.02, '2021-03-24': 41.01, '2021-03-25': 42.2, '2021-03-26': 42.53, '2021-03-29': 43.28, '2021-03-30': 43.88, '2021-03-31': 41.0}; 2.日涨跌幅（%）:{'2021-03-01': 1.3032, '2021-03-02': -1.265, '2021-03-03': 1.759, '2021-03-04': -2.7102, '2021-03-05': -1.0748, '2021-03-08': -3.4368, '2021-03-09': -4.248, '2021-03-10': -1.9664, '2021-03-11': 1.7123, '2021-03-12': -0.9861, '2021-03-15': -3.3277, '2021-03-16': 2.1859, '2021-03-17': 2.2867, '2021-03-18': -1.226, '2021-03-19': -1.5089, '2021-03-22': 0.8401, '2021-03-23': 0.5146, '2021-03-24': -0.0244, '2021-03-25': 2.9017, '2021-03-26': 0.782, '2021-03-29': 1.7635, '2021-03-30': 1.3863, '2021-03-31': -6.5634}; 3.日成交量（亿):{'2021-03-01': 78295.76, '2021-03-02': 102856.17, '2021-03-03': 86152.49, '2021-03-04': 109813.73, '2021-03-05': 101317.58, '2021-03-08': 156474.0, '2021-03-09': 191593.53, '2021-03-10': 116544.49, '2021-03-11': 107882.75, '2021-03-12': 78482.78, '2021-03-15': 150044.54, '2021-03-16': 82166.79, '2021-03-17': 122185.97, '2021-03-18': 86142.73, '2021-03-19': 78510.91, '2021-03-22': 68607.33, '2021-03-23': 59836.95, '2021-03-24': 53532.07, '2021-03-25': 90866.25, '2021-03-26': 92890.75, '2021-03-29': 80064.21, '2021-03-30': 99855.56, '2021-03-31': 305925.66}",
        "generated_question": "关于双汇发展（000895）的2020年报，其主营业务表现如何？是否受到屠宰业务的影响？公司渠道分析和进口肉使用量对成本控制有何影响？股票近期市场表现如何，包括价格、涨跌幅和成交量的变化？",
        "trend_keywords": [],
        "year_keywords": [
          "2020",
          "2021"
        ],
        "term_keywords": [],
        "context_trend_score": 0,
        "context_year_score": 2,
        "context_term_score": 0,
        "question_trend_score": 0,
        "question_year_score": 0,
        "question_term_score": 0,
        "trend_score": 0,
        "year_score": 2,
        "term_score": 0,
        "total_score": 2,
        "context_score": 2,
        "diversity_score": 0.0
      },
      {
        "sample_id": "unknown",
        "summary": "赤峰黄金在2022年的业绩未能达到预期，主要原因是矿石品位下降、原材料价格上涨和所得税负担增加。公司计划在2023年维持黄金产量保守目标，同时通过内增和外扩策略加快海外资产布局。内增方面，公司参与铁拓矿业的投资并加强在西非的战略布局；外扩方面，与沙特合作开展金矿勘探项目，并收购新恒河矿业和洱源溪灯坪金矿的股权。此外，公司推出第二期员工持股计划，旨在推动公司发展。截至4月3日，股价为18元，最近一周股价波动较小，整体趋势呈下跌趋势。",
        "content": "研报题目是:赤峰黄金（600988）：内增外扩两手抓，加快海外资产布局；目标价格是目标价格未公布，评分是7.0；研报摘要:内增外扩两手抓，加快海外资产布局事件 公司发布2022年度报告2023年3月31日，赤峰黄金发布2022年度报告。2022年，公司实现营收62 67亿元，同比增长65 67 ，主要系金星资源纳入合并范围及万象矿业黄金产销量增加 归母净利润4 51亿元，同比下降22 57 扣非归母净利4 01亿元，同比下降24 90 。公司盈利不及预期，有三个方面的原因 1 一是2022年度矿石品位较上年度有所下降，原材料、能源价格上升导致材料费和电费较上年度大幅上涨，单位成本上升 2 金星资源纳入合并范围后所得税有效税负率上升 3 并购过程中形成的评估增值在本年度摊销金额较大。主要产品为矿产金 电解铜 锌精粉，其营收分别为53 05亿元 3 93亿元 1 74亿元，分别占比总营收84 65 6 28 2 78 。其中，矿产金是公司毛利主要来源 2022年，矿产金毛利润为14 66亿元，占比总毛利81 67 。2023年，公司将保守计划黄金产量，重点关注降本控费。全年预计实现销售收入65亿元人民币，实现归属于母公司的净利润不低于6 5亿元人民币。黄金产量首次突破10吨，迈向大型黄金矿企2022年，公司生产矿产金13 57吨，较上年增长67 61 ，公司黄金产量首次突破10吨 电解铜0 64万吨，较上年增长28 16 。2023年经营计划 矿产金产量计划不低于14 6吨，电解铜6 670吨，铜铅锌精粉23 800吨，钼精粉400吨。内增外扩两手抓，加快海外资产布局积极开拓与并购资源，加速布局海外业务。公司通过认购增发股份、竞标摘牌、二级市场增持等方式投资澳大利亚上市公司铁拓矿业，截至2022末持有其已发行股份的13 05 ，加强了在西非这一全球重要产金区域的战略布局。公司与沙特阿吉兰兄弟控股集团在沙特境内合作开展金矿勘探项目，这是公司以较低成本和风险，培育潜在优质项目的尝试，以期打开中东金矿资源开发良好局面。收购新恒河矿业51 股权，赋能黄金主业。取得云南洱源溪灯坪金矿控股权，其采矿权、探矿权内已探明资源矿石量 探明 控制 推断 1028 5万吨，平均品位1 32g t，金金属量13 558吨。该项目处于建设期，一期设计采选规模为14万吨 年，待探矿权转采矿权后，采选规模和黄金产量将进一步提高。员工持股计划有序推进，利好公司发展第二期员工持股计划参与人数不超过120人，截止截至2023年1月16日，公司通过集中竞价交易方式已累计回购股份1657 54万股，占公司总股本的0 9962 ，已支付的资金总额为人民币30076 00万元。同时，下面我提供的一份该股票的近期市场数据， 提示:我提供的数据一般是由三个字段组成，分别是每个对应日期的股票价格，涨跌幅，成交量数据。 数据如下: 1.该企业的近期数据如下:1.股票价格（元）:{'2023-04-03': 18.0, '2023-04-04': 18.47, '2023-04-06': 18.75, '2023-04-07': 18.2, '2023-04-10': 18.06, '2023-04-11': 18.53, '2023-04-12': 18.94, '2023-04-13': 18.56, '2023-04-14': 18.66, '2023-04-17': 18.35, '2023-04-18': 18.18, '2023-04-19': 18.09, '2023-04-20': 17.87, '2023-04-21': 17.64, '2023-04-24': 16.44, '2023-04-25': 16.23, '2023-04-26': 16.35, '2023-04-27': 16.53, '2023-04-28': 16.57}; 2.日涨跌幅（%）:{'2023-04-03': -0.8264, '2023-04-04': 2.6111, '2023-04-06': 1.516, '2023-04-07': -2.9333, '2023-04-10': -0.7692, '2023-04-11': 2.6024, '2023-04-12': 2.2126, '2023-04-13': -2.0063, '2023-04-14': 0.5388, '2023-04-17': -1.6613, '2023-04-18': -0.9264, '2023-04-19': -0.495, '2023-04-20': -1.2161, '2023-04-21': -1.2871, '2023-04-24': -6.8027, '2023-04-25': -1.2774, '2023-04-26': 0.7394, '2023-04-27': 1.1009, '2023-04-28': 0.242}; 3.日成交量（亿):{'2023-04-03': 467329.42, '2023-04-04': 518214.15, '2023-04-06': 614484.24, '2023-04-07': 487605.51, '2023-04-10': 375828.34, '2023-04-11': 469045.4, '2023-04-12': 608064.61, '2023-04-13': 370246.51, '2023-04-14': 422581.76, '2023-04-17': 370833.91, '2023-04-18': 312960.9, '2023-04-19': 243905.22, '2023-04-20': 306636.41, '2023-04-21': 252026.51, '2023-04-24': 637181.97, '2023-04-25': 397560.57, '2023-04-26': 176247.77, '2023-04-27': 194173.08, '2023-04-28': 188380.03}",
        "generated_question": "根据研报分析，赤峰黄金（600988）在2022年的业绩表现如何？公司未来有何战略规划？以及近期市场数据显示，该股票的走势如何？",
        "trend_keywords": [],
        "year_keywords": [
          "2023",
          "2022"
        ],
        "term_keywords": [],
        "context_trend_score": 0,
        "context_year_score": 2,
        "context_term_score": 0,
        "question_trend_score": 0,
        "question_year_score": 0,
        "question_term_score": 0,
        "trend_score": 0,
        "year_score": 2,
        "term_score": 0,
        "total_score": 2,
        "context_score": 2,
        "diversity_score": 0.0
      },
      {
        "sample_id": "unknown",
        "summary": "荣盛石化（002493）2023年一季度报告指出，虽然归母净利润同比下滑，但环比有所改善，主要由于毛利率回升。公司炼化能力强，产品产能持续释放，PTA和聚酯项目即将投产。上游与沙特阿美合作保障原料供应，下游布局新材料领域。预计未来几年公司净利润将增长，当前估值合理，维持推荐评级。市场数据显示，近期股价呈下跌趋势。",
        "content": "研报题目是:荣盛石化（002493）2023年一季报点评：盈利环比改善，长期成长无虞；目标价格是目标价格未公布，评分是5.0；研报摘要:事件 2023年4月26日，公司发布了2023年第一季度报告。2023年第一季度，公司营业收入为697 21亿元，同比增长1 63 归母净利润为 14 68亿元，同比下滑147 11 扣非归母净利润为 15 73亿元，同比下滑152 75 。其中，公司非经常性损益为1 05亿元，包含政府补助0 48亿元。环比22Q4业绩有所改善。23Q1，公司归母净利润为 14 68亿元，同比出现大幅下滑，但环比22Q4的 21 10亿元有所改善。主要是公司毛利率出现了回升，23Q1公司实现毛利率为4 35 ，环比22Q4的 0 86 提升了5 22pct。规模化炼化能力强，主要产品产能持续释放。炼化板块，截至2022年末，浙石化拥有1180万吨 年的芳烃和420万吨 年的烯烃生产能力，作为世界级炼化一体化项目，具有明显的规模优势，且其还具有工艺先进、原料适应性强、加工手段灵活的优势。PTA板块，公司预计250万吨 年PTA项目和180万吨 年聚酯瓶片装置将于今年陆续投产，且另外9万吨食品级再生聚酯瓶片产能正在推进，投产后海南逸盛将成为国内最大的食品级rPET供应商。聚酯板块，永盛高端薄膜的产能在不断拓展，今年将有15万吨的生产线进行投放 盛元二期50万吨差别化纤维项目，主要生产阻燃、功能性、免染纤维产品，也在积极推进过程当中。上游拟引入沙特阿美战略投资者，下游积极进军新材料。上游方面，2023年3月27日，控股股东浙江荣盛控股集团有限公司与沙特阿美全资子公司AOC签署了 股份买卖协议 ，拟将荣盛石化总股本的10 加一股 10 13亿股 ，以24 3元 股的价格转让给AOC，同时，双方签订了一系列 战略合作协议 。在上游资源趋紧的背景下，双方的合作保障了公司长期稳定的原料供应，同时，沙特阿美还将为公司提供海外销售渠道和炼油技术指导，有助于公司的良性发展。下游方面，公司瞄准高端新材料赛道，依托于浙石化和中金石化，通过成立荣盛新材料子公司聚焦高端聚烯烃、特种橡胶及弹性体、工程塑料、精细化工品和专用化工品、前沿新材料等领域。投资建议 随着下游需求逐步复苏，石化产品价差有望修复，且公司新材料等项目在逐步推进。我们预计，2023 2025年，公司归母净利润分别为55 08 71 73 94 39亿元，EPS分别为0 54 0 71 0 93元 股，对应2023年4月26日的PE分别为24 19 14倍，维持 推荐 评级。风险提示 原油价格波动的风险 主营产品价格下降的风险 新增产能投放速度较慢的风险 协议落地不及预期的风险。同时，下面我提供的一份该股票的近期市场数据， 提示:我提供的数据一般是由三个字段组成，分别是每个对应日期的股票价格，涨跌幅，成交量数据。 数据如下: 1.该企业的近期数据如下:1.股票价格（元）:{'2023-04-03': 14.92, '2023-04-04': 14.47, '2023-04-06': 14.68, '2023-04-07': 15.52, '2023-04-10': 15.13, '2023-04-11': 15.01, '2023-04-12': 14.82, '2023-04-13': 14.66, '2023-04-14': 14.48, '2023-04-17': 14.76, '2023-04-18': 14.48, '2023-04-19': 14.25, '2023-04-20': 13.85, '2023-04-21': 13.29, '2023-04-24': 13.18, '2023-04-25': 13.12, '2023-04-26': 13.11, '2023-04-27': 12.87, '2023-04-28': 13.22}; 2.日涨跌幅（%）:{'2023-04-03': -1.388, '2023-04-04': -3.0161, '2023-04-06': 1.4513, '2023-04-07': 5.7221, '2023-04-10': -2.5129, '2023-04-11': -0.7931, '2023-04-12': -1.2658, '2023-04-13': -1.0796, '2023-04-14': -1.2278, '2023-04-17': 1.9337, '2023-04-18': -1.897, '2023-04-19': -1.5884, '2023-04-20': -2.807, '2023-04-21': -4.0433, '2023-04-24': -0.8277, '2023-04-25': -0.4552, '2023-04-26': -0.0762, '2023-04-27': -1.8307, '2023-04-28': 2.7195}; 3.日成交量（亿):{'2023-04-03': 2008834.79, '2023-04-04': 1604542.63, '2023-04-06': 1143378.06, '2023-04-07': 2167203.55, '2023-04-10': 1307287.54, '2023-04-11': 811870.22, '2023-04-12': 895184.79, '2023-04-13': 786156.82, '2023-04-14': 677060.08, '2023-04-17': 1045819.4, '2023-04-18': 589577.26, '2023-04-19': 583477.36, '2023-04-20': 830662.8, '2023-04-21': 647521.92, '2023-04-24': 487578.4, '2023-04-25': 649144.2, '2023-04-26': 435575.93, '2023-04-27': 789348.28, '2023-04-28': 471211.96}",
        "generated_question": "荣盛石化（002493）2023年一季度的盈利情况如何？",
        "trend_keywords": [],
        "year_keywords": [
          "2025",
          "2023"
        ],
        "term_keywords": [],
        "context_trend_score": 0,
        "context_year_score": 2,
        "context_term_score": 0,
        "question_trend_score": 0,
        "question_year_score": 0,
        "question_term_score": 0,
        "trend_score": 0,
        "year_score": 2,
        "term_score": 0,
        "total_score": 2,
        "context_score": 2,
        "diversity_score": 0.0
      },
      {
        "sample_id": "unknown",
        "summary": "恒生电子的业绩在2019年实现了高速增长，预计全年净利润同比增长约100%-108%。收入方面，Q1-Q3期间收入分别同比增长11%-28%，费用控制表现良好，研发费用率略有提升。公司业绩增长主要得益于科创板、资管新规等政策带来的订单落地，预计未来MOM、金融开放、新三板改革等政策将持续推动业绩增长。恒生电子作为金融行业IT解决方案提供商，在多个领域有较高市场份额，看好其在金融行业上云趋势下的发展。给予买入评级。",
        "content": "研报题目是:恒生电子（600570）：业绩高速增长，成长继续加速；目标价格是目标价格未公布，评分是7.0；研报摘要:投资要点公司发布业绩预告 预计2019年年度实现归属于上市公司股东的净利润约为12 91亿元 13 42亿元，同比增长约100 到108 。预计实现归属于上市公司股东的扣除非经常性损益的净利润约为7 74亿元 8 15亿元，同比增长约50 58 。成长继续加速。收入侧，2019年Q1 Q2 Q3，公司分别实现营收5 90亿元 9 32亿元 7 73亿元，同比增长11 17 12 49 28 42 。费用侧，2019年前三季度公司销售费用率、管理费用率为31 28 13 91 ，较去年同期分别下降0 01pct 0 64pct，全年费用控制有望持续改善。前三季度研发费用率45 41 ，同比上升0 67pct，研发投入维持高位。利润侧，2019年Q1 Q4，公司累计实现扣非净利润0 36 2 56 3 17 7 95亿元 以业绩预告中位数估算 ，同比增长5 3 14 55 36 12 54 ，成长继续加速。政策持续催化，资本市场IT迎来快速发展期。随着资本市场改革的持续深化，资本市场IT迎来快速发展期。2019年，公司业绩增长主要受益于科创板、资管新规等订单的逐步落地，我们预计2020年，MOM 金融开放 新三板改革等政策有望持续给公司带来业绩增量，后续业绩有望持续高速成长。资本市场IT空间广阔，公司有望抢占行业上云先机。公司所处的资本市场IT行业空间广阔。我们认为，随着金融机构业务需求的变化、云计算技术的完善和金融科技政策的发展，金融行业上云有望迎来拐点。2019年12月，恒生电子联合阿里云发布了NewCloud金融领域云解决方案，未来将与阿里云、金融机构、云生态伙伴一起，推动金融机构上云。恒生电子在金融行业耕耘24年，随着金融行业的发展而成长，积累了大量的金融业务知识和经验，具有广泛的客户基础。公司的IT产品和解决方案覆盖证券、银行、基金、期货、信托、保险、交易所、私募和众筹等多个领域，并且各领域核心系统中都拥有较高的市场份额，看好公司抢占金融行业上云先机。投资建议 根据公司业绩预告，上调公司盈利预测，预计2019 2020 2021年EPS1 64 1 98 2 52元，对应PE47 41 39 17 30 80倍，给予 买入 评级。风险提示 业务进展不及预期，市场竞争加剧，政策发展不及预期同时，下面我提供的一份该股票的近期市场数据， 提示:我提供的数据一般是由三个字段组成，分别是每个对应日期的股票价格，涨跌幅，成交量数据。 数据如下: 1.该企业的近期数据如下:1.股票价格（元）:{'2020-01-02': 79.44, '2020-01-03': 79.03, '2020-01-06': 80.0, '2020-01-07': 81.6, '2020-01-08': 80.9, '2020-01-09': 82.07, '2020-01-10': 81.38, '2020-01-13': 82.47, '2020-01-14': 81.59, '2020-01-15': 83.4, '2020-01-16': 83.65, '2020-01-17': 87.4, '2020-01-20': 87.41, '2020-01-21': 87.78, '2020-01-22': 92.25, '2020-01-23': 88.69}; 2.日涨跌幅（%）:{'2020-01-02': 2.1999, '2020-01-03': -0.5161, '2020-01-06': 1.2274, '2020-01-07': 2.0, '2020-01-08': -0.8578, '2020-01-09': 1.4462, '2020-01-10': -0.8407, '2020-01-13': 1.3394, '2020-01-14': -1.0671, '2020-01-15': 2.2184, '2020-01-16': 0.2998, '2020-01-17': 4.483, '2020-01-20': 0.0114, '2020-01-21': 0.4233, '2020-01-22': 5.0923, '2020-01-23': -3.8591}; 3.日成交量（亿):{'2020-01-02': 175683.22, '2020-01-03': 163653.21, '2020-01-06': 210235.58, '2020-01-07': 227288.11, '2020-01-08': 230313.96, '2020-01-09': 179525.16, '2020-01-10': 130013.1, '2020-01-13': 158666.52, '2020-01-14': 125122.07, '2020-01-15': 179759.02, '2020-01-16': 170846.8, '2020-01-17': 296267.66, '2020-01-20': 289744.94, '2020-01-21': 203083.34, '2020-01-22': 266181.37, '2020-01-23': 288500.56}",
        "generated_question": "恒生电子（600570）在2019年的业绩表现如何？预计未来增长趋势如何？",
        "trend_keywords": [],
        "year_keywords": [
          "2020",
          "2019"
        ],
        "term_keywords": [],
        "context_trend_score": 0,
        "context_year_score": 2,
        "context_term_score": 0,
        "question_trend_score": 0,
        "question_year_score": 0,
        "question_term_score": 0,
        "trend_score": 0,
        "year_score": 2,
        "term_score": 0,
        "total_score": 2,
        "context_score": 2,
        "diversity_score": 0.0
      },
      {
        "sample_id": "unknown",
        "summary": "圣农发展（002299）的业绩受到鸡肉价格波动的影响，尽管通过一体化布局减少了风险。鸡肉价格下跌趋势有限，熟食转换率和2C端的发展有助于提升利润率。公司内部管理和成本优化成果显著，但财务费用略有增加。建议长期持有。",
        "content": "研报题目是:圣农发展（002299）：鸡肉价格拖累业绩，一体化布局优势显著；目标价格是目标价格未公布，评分是5.0；研报摘要:圣农发展 002299 事件 2020 年 7 月 21 日，公司发布 2020 年半年度报告。报告期内公司实现营业收入约 65 亿元，同比下降 0 82 实现归属于上市公司股东的净利润为 13 32 亿元，同比下降 19 4 。点评业绩受累于鸡肉价格波动，全产业链布局减少风险 分季度来看，Q1 公司实现营业收入 29 9 亿元，同比下降 3 2 ，实现归母净利润 7亿元，同比增长 7 3 。 Q2 公司实现营业收入 35 1 亿元，同比增长 1 3 ，受累于鸡肉价格的下滑，Q2 公司共计提 450 8 万元资产减值损失，实现归母净利润 6 3 亿元，同比减少 36 9 。目前，公司依托全资子公司圣泽生物，积极从事白羽肉鸡的育种工作，从而实现祖代鸡全部自给有余，并进一步进行全产业链的一体化布局，积极向猪肉及牛肉深加工领域拓展。未来公司产品的综合利用率与附加值将得到提升，抵抗鸡肉价格波动风险的能力有望进一步加强。鸡肉价格下跌空间有限，公司业绩有望得到改善 受新冠疫情对餐饮行业的冲击和上半年肉鸡出栏持续增加，鸡产品价格大幅下降。在供需两方承压的背景下，公司 2020H1 的整体毛利率 为 26 93 4 77 ，其中家禽饲养加工业务的毛利率为 24 23 6 41 ，食品业务毛利率为 34 56 2 78 。2020 年 Q2 全国主产区鸡产品均价 11340 元 吨，同比下降 16 8 ，环比下降 10 9 。随着猪肉价格持续上涨，鸡肉替代消费增加，以及 Q3 白羽肉鸡行业消费旺季的到来，鸡产品的下游需求正逐步恢复，预计未来鸡肉价格大幅下跌空间有限。熟食转换率稳定提升，2C 端发展迅速 2020 年 H1，公司家禽饲养加工业务营业收入 41 45 亿元，同比下降 6 25 ，食品业务营业收入18 67 亿元，同比增长 4 30 ，这主要受熟食占营收的比重同比增长4 43 影响。此外，公司借助电商平台，拓展 2C 渠道，2020H1 公司2C 渠道销售额同比增长高达 137 4 。随着公司内部生熟转化率持续提升，渠道布局的深入，拉动公司肉制品板块利润率提升，并打开公司长期盈利空间。费用及养殖成本进一步改善，降本增益成果凸显。2020 年上半年，公司深挖内部管理，积极降低资金成本，加大还款力度，实现养殖板块单吨鸡肉完全成本较上年同期下降 1 72 ，养殖板块单羽肉鸡费用较上年同期下降 27 45 。随着规模的扩张，公司销售费用和管理费用分别同比上升 2 25 及 26 10 ，销售费用率及管理费用率分别 2 68 及 1 95 ，分别同比增加 0 08 pct 及 0 45 pct。但为了减少财务费用，公司尽量保持较小的有息负债规模， 2020 年 H1 公司有息负债为 31 01 亿元，环比微增 3 66 ，同比大幅减少 28 46 ，促进公司财务费用同比下降 30 82 ，财务费用率同比减少 0 43 pct。投资建议 我们预计公司 2020 年 2022 年的净利润分别为 22 24 亿元，27 07 亿元， 31 87 亿元， EPS 分别为 1 79 2 18 2 57 元 股，给予增持 A评级。风险提示 疫情发生的风险，鸡肉价格波动的风险，原材料成本上升的风险。同时，下面我提供的一份该股票的近期市场数据， 提示:我提供的数据一般是由三个字段组成，分别是每个对应日期的股票价格，涨跌幅，成交量数据。 数据如下: 1.该企业的近期数据如下:1.股票价格（元）:{'2020-07-01': 29.97, '2020-07-02': 28.82, '2020-07-03': 28.17, '2020-07-06': 28.5, '2020-07-07': 28.6, '2020-07-08': 28.81, '2020-07-09': 29.75, '2020-07-10': 28.86, '2020-07-13': 31.46, '2020-07-14': 30.4, '2020-07-15': 30.75, '2020-07-16': 28.53, '2020-07-17': 29.04, '2020-07-20': 29.49, '2020-07-21': 29.17, '2020-07-22': 29.03, '2020-07-23': 28.12, '2020-07-24': 27.71, '2020-07-27': 27.47, '2020-07-28': 28.37, '2020-07-29': 28.52, '2020-07-30': 28.93, '2020-07-31': 28.7}; 2.日涨跌幅（%）:{'2020-07-01': 3.3448, '2020-07-02': -3.8372, '2020-07-03': -2.2554, '2020-07-06': 1.1715, '2020-07-07': 0.3509, '2020-07-08': 0.7343, '2020-07-09': 3.2628, '2020-07-10': -2.9916, '2020-07-13': 9.009, '2020-07-14': -3.3694, '2020-07-15': 1.1513, '2020-07-16': -7.2195, '2020-07-17': 1.7876, '2020-07-20': 1.5496, '2020-07-21': -1.0851, '2020-07-22': -0.4799, '2020-07-23': -3.1347, '2020-07-24': -1.458, '2020-07-27': -0.8661, '2020-07-28': 3.2763, '2020-07-29': 0.5287, '2020-07-30': 1.4376, '2020-07-31': -0.795}; 3.日成交量（亿):{'2020-07-01': 206991.6, '2020-07-02': 251562.3, '2020-07-03': 245888.31, '2020-07-06': 246465.26, '2020-07-07': 303547.27, '2020-07-08': 207784.1, '2020-07-09': 273286.6, '2020-07-10': 264507.03, '2020-07-13': 389797.65, '2020-07-14': 305970.7, '2020-07-15': 251510.4, '2020-07-16': 225258.32, '2020-07-17': 194477.98, '2020-07-20': 179491.85, '2020-07-21': 152613.84, '2020-07-22': 368654.4, '2020-07-23': 217688.41, '2020-07-24': 242843.68, '2020-07-27': 136570.72, '2020-07-28': 165490.95, '2020-07-29': 122855.54, '2020-07-30': 182499.87, '2020-07-31': 133805.58}",
        "generated_question": "基于圣农发展的业绩报告和近期市场数据，如何评估其下一个月的股价变动方向及其概率？",
        "trend_keywords": [],
        "year_keywords": [
          "2020",
          "2022"
        ],
        "term_keywords": [],
        "context_trend_score": 0,
        "context_year_score": 2,
        "context_term_score": 0,
        "question_trend_score": 0,
        "question_year_score": 0,
        "question_term_score": 0,
        "trend_score": 0,
        "year_score": 2,
        "term_score": 0,
        "total_score": 2,
        "context_score": 2,
        "diversity_score": 0.0
      },
      {
        "sample_id": "unknown",
        "summary": "2017年是中国实施‘十三五’规划的关键年份，也是深化供给侧结构性改革的一年。会议强调改革目标为满足需求，提升供给质量，实现路径为深入改革。2017年的改革重心在于推进'三去一降一补'，包括优化产能、消化库存、降杠杆、降低成本和补齐短板，以加速经济转型。",
        "content": "2016-12-18_;中央经济工作会议指出，2017年是实施“十三五”规划的重要一年，也是供给侧结构性改革的深化之年。作为中国未来一段时期的经济工作主线，供给侧结构性改革有了新的内涵、新的任务。面对世界经济复杂多变的形势，面对中国经济结构突出的矛盾和问题，中央经济工作会议对供给侧结构性改革做了新的阐述：改革的最终目的是满足需求，主攻方向是提高供给质量，根本途径是深化改革。2017年，供给侧结构性改革将进一步深化，重点明确了四个方向：一是推动“三去一降一补”取得实质性进展；二是深入推进农业供给侧结构性改革；三是着力振兴实体经济；四是促进房地产市场平稳健康发展。2017年，“三去一降一补”五大任务内涵有了新扩充，改革将面向更多的硬骨头。去产能，要抓住处置“僵尸企业”这个牛鼻子，同时从钢铁和煤炭，向其他过剩行业扩围；去库存，要重点解决三四线城市房地产库存过多问题；去杠杆，要把降低企业杠杆率作为重中之重；降成本，要在降低各类交易成本特别是制度性交易成本上做文章；而补短板，则既要补硬短板也要补软短板，既补发展短板也补制度短板。通过供给侧结构性改革的不断深化，推动中国经济加快转型升级。",
        "generated_question": "2017年中央经济工作会议如何定义供给侧结构性改革的目标、主攻方向和根本途径？并指出了当年改革的重点是什么？",
        "trend_keywords": [],
        "year_keywords": [
          "2016",
          "2017"
        ],
        "term_keywords": [],
        "context_trend_score": 0,
        "context_year_score": 2,
        "context_term_score": 0,
        "question_trend_score": 0,
        "question_year_score": 0,
        "question_term_score": 0,
        "trend_score": 0,
        "year_score": 2,
        "term_score": 0,
        "total_score": 2,
        "context_score": 2,
        "diversity_score": 0.0
      },
      {
        "sample_id": "unknown",
        "summary": "招商银行业绩发布会讨论了疫情对其零售信贷的短期影响及全年资产质量的控制能力。强调了管理团队在风险上行时的高质量管理和业务策略。公司预计2020年资产和负债规模保持稳定增长，重点投向房贷、战略对公客户及特定行业。LPR改革影响预计在2021年体现，NIM预计将优于同业。资产质量压力在第一季度有所增加，但管理层预计全年较为可控。公司将继续坚持一体两翼战略，加大零售业务投入，保持收入和风险结构的平稳。理财子公司业务转型的核心目标是做大净值型产品的规模，分红比例有望提升。估值建议维持原有盈利预测，目标价为51元人民币，较当前股价有69%的上行空间。",
        "content": "研报题目是:招商银行（600036）：业绩发布会纪要：风险上行时的高质量管理团队和业务；目标价格是51.0，评分是5.0；研报摘要:招商银行 600036 公司动态公司近况招商银行3月23日组织召开2019年业绩发布会，就疫情影响、LPR下调影响、未来发展战略等问题与投资者和媒体进行了交流。评论新冠疫情对零售信贷有负面影响，但全年压力不大。2019年虽然信用卡不良生成较快，但招行自2017年就关注共债风险，并对获客、信贷投放采取收缩策略，并快速释放风险进行核销，全年总体信贷质量最终稳中向好。2020年，新冠疫情对信用卡、消费贷等零售业务有资产质量压力，也影响了清收产能 40 在湖北 ，我们预计未来几个季度不良率有上升压力 考虑到信用卡交易额已快速回升，且银行拨备重组，我们预计全年资产质量压力较为可控。2020年资产负债规模保持稳定增长，增速10 左右。招行将坚持一体两翼战略，认为零售业务其营收占比升至约60 水平较为合适 2019年 55 适当的公司业务和资金业务占比则有利于保持收入和风险结构的平稳。2020年，招行资产方面着重投向房贷、总行和分行战略对公客户 行业方面主要是基建、新动能、高端制造 ，信用卡增速会下降。负债目标增速是M2增速 2个百分点 强化核心存款的增长，对主动负债加强限额管理。LPR改革影响体现在2021年 NIM仍将优于同业。招行在2019年逐步拉长贷款和投资资产久期，提高固定利率贷款占比，NIM全年略有上行。由于存量贷款LPR定价改革以等价转换为原则，对NIM的影响将主要体现在2021年。在利率中枢下行环境下，招行管理层预计NIM也有下行压力，但有信心继续保持优于同业。资管争取做大规模。理财子后，业务转型核心目标是做大理财管理的规模 净值型产品的规模 ，我们预计相应收入会重回增长轨道。分红比例争取能有提高。管理层将2019年分红比例提高至33 。发布会上，管理层表示在满足监管要求、业务发展需要情况下，争取能提高分红比例，更好回馈投资者。估值建议维持2020年和2021年盈利预测不变。目前招商银行A H股交易于1 19x 1 22x2020ePB。维持A H股跑赢行业评级和51元人民币 57元港币目标价，对应2 0x 1 9x2020年市净率，较当前股价有69 1 79 8 的上行空间。风险疫情影响范围和持续时间超预期 资产质量恶化超预期。同时，下面我提供的一份该股票的近期市场数据， 提示:我提供的数据一般是由三个字段组成，分别是每个对应日期的股票价格，涨跌幅，成交量数据。 数据如下: 1.该企业的近期数据如下:1.股票价格（元）:{'2020-03-02': 34.75, '2020-03-03': 34.62, '2020-03-04': 34.78, '2020-03-05': 36.23, '2020-03-06': 35.41, '2020-03-09': 34.18, '2020-03-10': 34.68, '2020-03-11': 34.45, '2020-03-12': 34.16, '2020-03-13': 33.41, '2020-03-16': 31.67, '2020-03-17': 31.73, '2020-03-18': 30.82, '2020-03-19': 29.31, '2020-03-20': 31.04, '2020-03-23': 30.16, '2020-03-24': 31.51, '2020-03-25': 32.49, '2020-03-26': 32.72, '2020-03-27': 32.72, '2020-03-30': 32.65, '2020-03-31': 32.28}; 2.日涨跌幅（%）:{'2020-03-02': 1.6082, '2020-03-03': -0.3741, '2020-03-04': 0.4622, '2020-03-05': 4.1691, '2020-03-06': -2.2633, '2020-03-09': -3.4736, '2020-03-10': 1.4628, '2020-03-11': -0.6632, '2020-03-12': -0.8418, '2020-03-13': -2.1956, '2020-03-16': -5.208, '2020-03-17': 0.1895, '2020-03-18': -2.8679, '2020-03-19': -4.8994, '2020-03-20': 5.9024, '2020-03-23': -2.8351, '2020-03-24': 4.4761, '2020-03-25': 3.1101, '2020-03-26': 0.7079, '2020-03-27': 0.0, '2020-03-30': -0.2139, '2020-03-31': -1.1332}; 3.日成交量（亿):{'2020-03-02': 704290.63, '2020-03-03': 686073.06, '2020-03-04': 560886.06, '2020-03-05': 1355413.0, '2020-03-06': 670673.78, '2020-03-09': 966591.66, '2020-03-10': 668298.1, '2020-03-11': 566550.64, '2020-03-12': 619180.02, '2020-03-13': 1140957.7, '2020-03-16': 1066027.3, '2020-03-17': 843441.33, '2020-03-18': 824317.04, '2020-03-19': 1559457.47, '2020-03-20': 1343153.1, '2020-03-23': 928971.16, '2020-03-24': 825358.93, '2020-03-25': 809526.55, '2020-03-26': 694635.85, '2020-03-27': 581775.45, '2020-03-30': 477494.15, '2020-03-31': 377540.06}",
        "generated_question": "招商银行(600036)在2020年的业绩发布会上宣布了哪些关键的业务策略和财务目标?",
        "trend_keywords": [],
        "year_keywords": [
          "2020",
          "2019"
        ],
        "term_keywords": [],
        "context_trend_score": 0,
        "context_year_score": 2,
        "context_term_score": 0,
        "question_trend_score": 0,
        "question_year_score": 0,
        "question_term_score": 0,
        "trend_score": 0,
        "year_score": 2,
        "term_score": 0,
        "total_score": 2,
        "context_score": 2,
        "diversity_score": 0.0
      },
      {
        "sample_id": "unknown",
        "summary": "建设机械（600984）上半年业绩有所增长，但第二季度受到信用减值损失的影响，利润增速放缓。第二季度公司业绩大幅回升。毛利率方面，第一季度因疫情下降，第二季度受益于下游需求回暖，利润率改善。费用率整体稳定，第二季度略有下降。净利率受信用减值损失影响，第二季度有所提升。在手订单稳步增长，塔机保有量突破7000台，利用率回升。预计未来公司净利润分别为75.5亿、108.9亿、141.1亿，给予买入A评级，6个月目标价34.2元。",
        "content": "研报题目是:建设机械（600984）：信用减值损失拖累利润增速，Q2公司业绩大幅回升；目标价格是34.2，评分是7.0；研报摘要:事件 公司公布2020年中报，2020年H1，营业收入15 35亿元，yoy 9 73 归母净利润1 61亿元，yoy 14 16 。Q2营收10 74亿元，yoy 25 83 归母净利润为2 23亿元，yoy 33 94 ，业绩略低于预期。信用减值损失拖累利润增速，Q2公司业绩大幅回升。2020H1公司毛利率为36 74 ，较2019H1变动 0 02pct。受疫情影响，2019Q1公司毛利率仅为18 77 ，Q2之后受益于下游需求的快速回暖，公司利润率改善突出，Q2公司毛利率为44 46 ，较2019Q2变动 2 5pct。公司降本增效效果显著，二季度费用大幅下滑。2020H1公司费用率合计为18 98pct，较2019H1变动 0 17pct，销售费用率 管理费用率 研发费用率 财务费用率 分别为0 79 7 28 3 77 7 14pct，较2019H1变动 0 36 0 74 0 35 0 91pct，费用率基本稳定。Q2公司费用率合计为14 96pct，较2019Q2变动 1 89pct，销售费用率 管理费用率 研发费用率 财务费用率 分别为0 68 6 15 3 01 5 12pct，较2019H1变动 0 23 1 12 0 02 0 52pct。2020H1净利率为10 49 ，较2019H1变动 2 94pct，主要原因在于公司计提了7366万元的信用减值损失，而去年同期为4126万元，对净利率影响在1 85pct左右。尽管如此，受益于毛利率的提升和费用率的有效控制，Q2之后公司盈利能力持续提升，单Q2公司净利率为20 70 ，较2019Q2变动 1 23pct。在手订单稳步增长，塔机保有量突破7000台，利用率回升明显。2020H1末，庞源租赁新签合同总额超过19 48亿元，同比增长12 54 ，在手合同延续产值23 17亿，同比增长40 77 。目前公司塔机保有量已经突破7000台，预计2020年塔机采购额仍会在25亿以上，规模扩张动力十足。从利用率看，庞源塔机7月利用率回升至72 9 的正常水平，下半年收入有望维持快速增长。公司背靠控股股东强大的融资能力，以极低成本迅速扩张。当前公司在国内市占率仅为3 左右，市占率提升空间巨大。并且公司在全国主要地区投资建设高标准的生产服务基地，公司在建、签订协议待建及达成意向的基地数量已达到17个，为有步骤地推进租赁与保障的细分经营模式奠定基础。投资建议 预计2020 2022年公司净利润分别为7 55亿元、10 89亿元和14 11亿元，对应EPS分别为0 76、1 09、1 42元。给与买入 A评级，6个月目标价34 2元，相当于2020年45X市盈率。风险提示 宏观经济大幅下滑、基建投资大幅下滑、疫情影响超预期。同时，下面我提供的一份该股票的近期市场数据， 提示:我提供的数据一般是由三个字段组成，分别是每个对应日期的股票价格，涨跌幅，成交量数据。 数据如下: 1.该企业的近期数据如下:1.股票价格（元）:{'2020-09-01': 26.93, '2020-09-02': 25.4, '2020-09-03': 24.44, '2020-09-04': 23.64, '2020-09-07': 22.46, '2020-09-08': 23.12, '2020-09-09': 23.4, '2020-09-10': 24.1, '2020-09-11': 23.68, '2020-09-14': 23.31, '2020-09-15': 24.03, '2020-09-16': 22.72, '2020-09-17': 22.83, '2020-09-18': 23.68, '2020-09-21': 22.78, '2020-09-22': 22.43, '2020-09-23': 22.72, '2020-09-24': 21.6, '2020-09-25': 21.91, '2020-09-28': 21.56, '2020-09-29': 20.85, '2020-09-30': 21.31}; 2.日涨跌幅（%）:{'2020-09-01': 5.1132, '2020-09-02': -5.6814, '2020-09-03': -3.7795, '2020-09-04': -3.2733, '2020-09-07': -4.9915, '2020-09-08': 2.9386, '2020-09-09': 1.2111, '2020-09-10': 2.9915, '2020-09-11': -1.7427, '2020-09-14': -1.5625, '2020-09-15': 3.0888, '2020-09-16': -5.4515, '2020-09-17': 0.4842, '2020-09-18': 3.7232, '2020-09-21': -3.8007, '2020-09-22': -1.5364, '2020-09-23': 1.2929, '2020-09-24': -4.9296, '2020-09-25': 1.4352, '2020-09-28': -1.5974, '2020-09-29': -3.2931, '2020-09-30': 2.2062}; 3.日成交量（亿):{'2020-09-01': 239122.55, '2020-09-02': 178961.9, '2020-09-03': 170663.84, '2020-09-04': 242154.22, '2020-09-07': 130527.11, '2020-09-08': 188315.24, '2020-09-09': 128994.64, '2020-09-10': 125472.58, '2020-09-11': 68107.5, '2020-09-14': 78418.03, '2020-09-15': 86792.84, '2020-09-16': 138058.14, '2020-09-17': 98499.04, '2020-09-18': 104342.61, '2020-09-21': 126488.06, '2020-09-22': 55120.66, '2020-09-23': 48032.79, '2020-09-24': 97990.25, '2020-09-25': 92828.37, '2020-09-28': 110622.2, '2020-09-29': 171027.15, '2020-09-30': 228067.94}",
        "generated_question": "根据提供的研究报告，建设机械（600984）在2020年的中报表现如何？",
        "trend_keywords": [],
        "year_keywords": [
          "2062",
          "2020"
        ],
        "term_keywords": [],
        "context_trend_score": 0,
        "context_year_score": 2,
        "context_term_score": 0,
        "question_trend_score": 0,
        "question_year_score": 0,
        "question_term_score": 0,
        "trend_score": 0,
        "year_score": 2,
        "term_score": 0,
        "total_score": 2,
        "context_score": 2,
        "diversity_score": 0.0
      },
      {
        "sample_id": "unknown",
        "summary": "恒生电子（600570）发布股票期权激励计划，调整授予数量至1666万份，占总股本的0.88%，不再设臵预留。激励计划涉及267人，包括12位董监高，激励力度高于2020年股权激励。计划对当期利润影响较小，预计成为公司人效提升的拐点。股票价格在公告发布后上涨至36.15元/股，较行权价格高出1.27元/股。股票期权授予对2022年至2025年的费用影响分别为1173万元至3545万元不等。预计2022年至2024年的营收增长目标为每年15%。维持公司买入评级。",
        "content": "研报题目是:恒生电子（600570）：股票期权授予靴子落地，短期交易面担忧消解；目标价格是目标价格未公布，评分是7.0；研报摘要:事件简评9月13日，公司发布向2022年股票期权激励计划激励对象首次授予股票期权的公告。由于公告草案发布后公司股价表现亮眼，授予日收盘价36 15元 股高于行权价格34 88元 份，因而拟授予股票期权数量由2 747万份调整至1 666万份，占总股本0 88 ，且不再设臵预留。经营分析授予速度超预期，且高额股票期权激励计划有利于使股东及公司骨干员工利益更加一致。本次激励对象涉及267人，其中12位董监高约需花费300至1 629万元不等，其他骨干员工平均约需花费188万元，激励力度高于2020年股权激励。本次股票期权激励计划涉及的董监高以新任管理层为主，有利于使得股东及公司核心骨干利益更加一致。本计划对当期利润影响较小，依然看好Q3成为公司人效提升拐点。本次股票期权授予对2022 2025年费用影响分别为1 173万 3 545万 2 068万 922万元，对当期净利影响不大。本次激励设臵的2022 2024年营收增速目标均为15 ，我们认为该增速主要是为了使得顺利达成激励骨干员工的目的，预期营收增速更加乐观。盈利调整根据本次股票期权激励计划对费用的影响预估，我们维持公司2022 2024年营收67 8 83 4 100 5亿元的盈利预测，将此前13 4 18 5 23 7的归母净利预测略微调降至13 3 18 2 23 5亿元。投资建议我们认为三季度收入端受益于上半年需求递延，成本费用端受益于人员增速放缓以及股份支付费用同比减少，有望成为公司转向控费期、人效提升的拐点。当前市值对应2022 2024年51 8 37 8 29 2 倍PE，依然处于近年公司较低的估值区间，维持 买入 评级。风险提示疫情扰动使得业务推进不及预期 非经常性损益不及预期 管理层减持风险 商誉减值风险同时，下面我提供的一份该股票的近期市场数据， 提示:我提供的数据一般是由三个字段组成，分别是每个对应日期的股票价格，涨跌幅，成交量数据。 数据如下: 1.该企业的近期数据如下:1.股票价格（元）:{'2022-09-01': 34.5, '2022-09-02': 34.37, '2022-09-05': 33.73, '2022-09-06': 33.66, '2022-09-07': 33.59, '2022-09-08': 33.99, '2022-09-09': 35.3, '2022-09-13': 36.15, '2022-09-14': 36.3, '2022-09-15': 35.71, '2022-09-16': 33.99, '2022-09-19': 33.69, '2022-09-20': 32.77, '2022-09-21': 32.74, '2022-09-22': 32.8, '2022-09-23': 32.52, '2022-09-26': 32.04, '2022-09-27': 33.67, '2022-09-28': 33.51, '2022-09-29': 33.52, '2022-09-30': 33.89}; 2.日涨跌幅（%）:{'2022-09-01': 2.5565, '2022-09-02': -0.3768, '2022-09-05': -1.8621, '2022-09-06': -0.2075, '2022-09-07': -0.208, '2022-09-08': 1.1908, '2022-09-09': 3.8541, '2022-09-13': 2.4079, '2022-09-14': 0.4149, '2022-09-15': -1.6253, '2022-09-16': -4.8166, '2022-09-19': -0.8826, '2022-09-20': -2.7308, '2022-09-21': -0.0915, '2022-09-22': 0.1833, '2022-09-23': -0.8537, '2022-09-26': -1.476, '2022-09-27': 5.0874, '2022-09-28': -0.4752, '2022-09-29': 0.0298, '2022-09-30': 1.1038}; 3.日成交量（亿):{'2022-09-01': 189720.69, '2022-09-02': 91981.15, '2022-09-05': 134083.24, '2022-09-06': 77778.72, '2022-09-07': 96410.33, '2022-09-08': 98483.63, '2022-09-09': 174598.87, '2022-09-13': 172314.25, '2022-09-14': 158008.74, '2022-09-15': 119620.63, '2022-09-16': 352262.12, '2022-09-19': 152995.55, '2022-09-20': 128915.22, '2022-09-21': 114324.38, '2022-09-22': 71268.97, '2022-09-23': 76431.89, '2022-09-26': 107828.4, '2022-09-27': 136165.96, '2022-09-28': 85974.84, '2022-09-29': 118994.06, '2022-09-30': 101960.81}",
        "generated_question": "基于恒生电子（600570）的股票期权激励计划和市场数据，该股票下个月的最终收益结果会如何预测？",
        "trend_keywords": [],
        "year_keywords": [
          "2075",
          "2022"
        ],
        "term_keywords": [],
        "context_trend_score": 0,
        "context_year_score": 2,
        "context_term_score": 0,
        "question_trend_score": 0,
        "question_year_score": 0,
        "question_term_score": 0,
        "trend_score": 0,
        "year_score": 2,
        "term_score": 0,
        "total_score": 2,
        "context_score": 2,
        "diversity_score": 0.0
      },
      {
        "sample_id": "unknown",
        "summary": "平煤股份(Q2)成本显著下降，商品煤盈利提升，2020上半年原煤产量及销量环比改善，成本下降幅度超过价格变动，吨煤毛利增加，盈利能力提升。公司持续高比例分红，股息率处于行业领先地位。预计2020年净利润为13.10亿元，股息率为6.55%，处于行业领先水平。维持买入A评级，6个月目标价为6.19元。",
        "content": "研报题目是:平煤股份（601666）：Q2成本大幅下降，商品煤盈利提升；目标价格是6.19，评分是7.0；研报摘要:事件 2020年7月30日，公司发布 2020年上半年经营数据公告，报告期内公司实现原煤产量1526 59万吨，同比增长6 48 ，实现商品煤销量1576 27万吨，同比下降4 31 。点评二季度产销环比改善明显 据公告测算，2020年二季度公司实现原煤产量766 29万吨，同比增长69 54万吨，增幅9 98 ，环比增长5 99万吨，增幅0 79 。销量方面，二季度销售商品煤872 04万吨，同比下降68 63万吨，降幅7 3 ，环比增长167 81万吨，增幅23 83 。二季度成本大幅下降，商品煤盈利提升 据公告测算，二季度公司商品煤吨煤收入为672 27元 吨，较一季度下降38 31元 吨，降幅5 39 ，较去年同时期增长2 04元 吨，增幅0 3 。二季度吨煤销售成本为482 75元 吨，较一季度下降70 58元 吨，降幅12 76 ，较去年同时期下降63 7元 吨，降幅11 66 。成本下降幅度远大于价格，因此吨煤毛利大幅提升，二季度公司吨煤毛利为189 53元 吨，较一季度增长32 28元 吨，较去年同时期增长65 73元 吨，毛利率为28 19 ，环比增长6 06个百分点，同比增长9 72个百分点，盈利能力大幅提升。未来持续高比例分红，股息率处于行业领先水平 据公告，2019年公司共计派发现金股利6 93亿元，占2019年属于上市公司股东的净利润的60 以7月30日市值测算股息率5 82 。据公司2019年至2021年股东分红回报规划，公司每年以现金方式分配的利润原则上不少于当年实现的合并报表可供分配利润的60 且每股派息不低于0 25元人民币。以每股0 25元派息测算，未来三年公司保底股息率4 87 基于2020年7月30日收盘价测算 。我们预计公司2020年可实现净利润13 10亿元，以60 的分红比例测算，股息率6 55 基于2020年7月30日收盘价 ，处于行业领先水平。投资建议 在盈利能力提高，资产负债表修复，现金流不断改善的背景下，公司有望保持长期稳定分红，同时估值也有望提升预计2020 2022年公司归母净利为13 10 13 99 14 78亿元，折合EPS分别为0 56 0 60 0 63。维持 买入 A 评级，6个月目标价6 19元。风险提示 宏观经济下行风险，下游需求萎缩风险 煤价大幅下跌，产量不及预期。同时，下面我提供的一份该股票的近期市场数据， 提示:我提供的数据一般是由三个字段组成，分别是每个对应日期的股票价格，涨跌幅，成交量数据。 数据如下: 1.该企业的近期数据如下:1.股票价格（元）:{'2020-07-01': 3.78, '2020-07-02': 3.88, '2020-07-03': 4.26, '2020-07-06': 4.69, '2020-07-07': 4.72, '2020-07-08': 4.84, '2020-07-09': 5.1, '2020-07-10': 4.78, '2020-07-13': 4.88, '2020-07-14': 4.93, '2020-07-15': 4.74, '2020-07-16': 4.64, '2020-07-17': 4.59, '2020-07-20': 4.84, '2020-07-21': 4.83, '2020-07-22': 4.75, '2020-07-23': 4.69, '2020-07-24': 4.58, '2020-07-27': 4.61, '2020-07-28': 4.7, '2020-07-29': 4.85, '2020-07-30': 5.13, '2020-07-31': 5.06}; 2.日涨跌幅（%）:{'2020-07-01': 1.0695, '2020-07-02': 2.6455, '2020-07-03': 9.7938, '2020-07-06': 10.0939, '2020-07-07': 0.6397, '2020-07-08': 2.5424, '2020-07-09': 5.3719, '2020-07-10': -6.2745, '2020-07-13': 2.0921, '2020-07-14': 1.0246, '2020-07-15': -3.854, '2020-07-16': -2.1097, '2020-07-17': -1.0776, '2020-07-20': 5.4466, '2020-07-21': -0.2066, '2020-07-22': -1.6563, '2020-07-23': -1.2632, '2020-07-24': -2.3454, '2020-07-27': 0.655, '2020-07-28': 1.9523, '2020-07-29': 3.1915, '2020-07-30': 5.7732, '2020-07-31': -1.3645}; 3.日成交量（亿):{'2020-07-01': 71665.22, '2020-07-02': 218484.45, '2020-07-03': 749454.44, '2020-07-06': 628409.92, '2020-07-07': 966801.33, '2020-07-08': 690530.82, '2020-07-09': 823813.21, '2020-07-10': 594826.96, '2020-07-13': 421605.59, '2020-07-14': 414285.41, '2020-07-15': 293013.86, '2020-07-16': 442195.02, '2020-07-17': 300233.06, '2020-07-20': 356704.17, '2020-07-21': 238621.41, '2020-07-22': 275564.16, '2020-07-23': 253111.58, '2020-07-24': 382376.25, '2020-07-27': 230781.27, '2020-07-28': 255234.12, '2020-07-29': 443034.76, '2020-07-30': 692489.51, '2020-07-31': 406212.89}",
        "generated_question": "平煤股份(Q2)的成本变化如何影响其商品煤盈利？",
        "trend_keywords": [],
        "year_keywords": [
          "2020",
          "2066"
        ],
        "term_keywords": [],
        "context_trend_score": 0,
        "context_year_score": 2,
        "context_term_score": 0,
        "question_trend_score": 0,
        "question_year_score": 0,
        "question_term_score": 0,
        "trend_score": 0,
        "year_score": 2,
        "term_score": 0,
        "total_score": 2,
        "context_score": 2,
        "diversity_score": 0.0
      }
    ],
    "term": [
      {
        "sample_id": "unknown",
        "summary": "一汽解放于2006年9月22日的股票分析数据显示，其股息率为6.4309%。",
        "content": "{'TS股票代码': '000800.SZ', '交易日': '2006-09-22', '换手率（%）': 0.6302, '市盈率（总市值/净利润， 亏损的PE为空）': 14.9916, '市销率（TTM）': 0.4857, '股息率（TTM）（%）': 6.4309, '总股本 （万股）': 162750.0, '流通股本 （万股）': 72615.5794, '总市值 （万元）': 506152.5}。",
        "generated_question": "一汽解放(000800.SZ)于2006年9月22日的股息率是多少？",
        "trend_keywords": [],
        "year_keywords": [
          "2006"
        ],
        "term_keywords": [
          "市盈率",
          "换手率",
          "市销率",
          "净利润"
        ],
        "context_trend_score": 0,
        "context_year_score": 1,
        "context_term_score": 4,
        "question_trend_score": 0,
        "question_year_score": 0,
        "question_term_score": 0,
        "trend_score": 0,
        "year_score": 1,
        "term_score": 4,
        "total_score": 5,
        "context_score": 5,
        "diversity_score": 0.0
      },
      {
        "sample_id": "unknown",
        "summary": "阳光电源在2023年4月24日的股票数据包括：股票代码300274.SZ，当日收盘价103.4元，量比1.26，市盈率97.0291，市销率6.3625，股息率0.1064%，自由流通股本96122.9317万。其中，市销率是6.3625。",
        "content": "{'TS股票代码': '300274.SZ', '交易日': '2023-04-24', '当日收盘价': 103.4, '量比': 1.26, '市盈率（总市值/净利润， 亏损的PE为空）': 97.0291, '市销率': 6.3625, '市销率（TTM）': 4.9559, '股息率 （%）': 0.1064, '股息率（TTM）（%）': 0.1064, '自由流通股本 （万）': 96122.9317}。",
        "generated_question": "阳光电源在2023年4月24日的市销率是多少？",
        "trend_keywords": [],
        "year_keywords": [
          "2023"
        ],
        "term_keywords": [
          "市盈率",
          "市销率",
          "净利润"
        ],
        "context_trend_score": 0,
        "context_year_score": 1,
        "context_term_score": 3,
        "question_trend_score": 0,
        "question_year_score": 0,
        "question_term_score": 0,
        "trend_score": 0,
        "year_score": 1,
        "term_score": 3,
        "total_score": 4,
        "context_score": 4,
        "diversity_score": 0.0
      },
      {
        "sample_id": "unknown",
        "summary": "报告指出创维数字（000810）短期内面临需求承压和收入下滑的压力，特别是智能终端业务在国内市场的表现不佳，但海外市场需求有所增长。报告下调了公司2020-2022年的EPS预测，并给出了公司的买入评级。短期内，收入及盈利承压，但报告认为中长期网络融合发展的趋势对公司有利。报告建议给予公司2021年18倍PE的目标价格。",
        "content": "研报题目是:创维数字（000810）：短期需求承压，收入结构影响利润；目标价格是11.16，评分是7.0；研报摘要:创维数字 000810 2020Q3 收入 归母净利同比 6 77 57 23 ，维持 买入 评级公司披露 2020 年三季报，2020Q1 Q3 公司实现营业总收入 59 37 亿元，同比 5 57 ，归母净利 2 81 亿元，同比 42 90 ，其中，2020Q3 营收同比 6 77 ，归母净利同比 57 23 。公司国内智能终端需求景气度依然偏低，海外需求虽有增长，但整体依然面临收入下滑压力。中长期内，我们看好公司继续发掘网络融合需求，拓展宽带接入设备收入空间，同时公司在专业显示领域合作稳定，受益于 5G 换机需求。 我们下调公司 2020 2022年 EPS 为 0 53、0 62、0 72 元，维持 买入 评级。2020Q3 收入仍同比下滑，智能终端业务或依然有压力2020Q3 收入同比 6 77 ，考虑到国内市场传统机顶盒需求减弱，公司主要与广电运营商及三大运营商合作，需求偏弱的背景下，智能终端业务内销或依然承压，相对而言，海外市场疫情影响明显，电视观看需求增长，或依然带来出口增长，综合内外销情况，我们预计智能终端收入依然有所下滑。而公司专业显示业务主要提供中小尺寸模组、车载显示等产品，受益于 5G 手机换机潮，我们预计专业显示业务收入延续 H1 表现，继续同比增长。2020Q3 产品毛利率同比大幅下滑受低毛利业务增长较快拖累，公司 2020Q1 Q3 毛利率 18 65 ，同比 3 77pct，其中 2020Q3 毛利率同比 5 50pct。 虽然原材料价格同比有所优化 2020 年 1 9 月，Wind 数据显示 DDR3 2Gb、DDR3 4Gb 均价分别同比 8 6 、 11 8 。 ，但公司低毛利专业显示业务收入占比或有提升，整体影响公司毛利率水平。2020Q3 期间费用率同比明显提升，主要受研发及财务费用率影响202020Q1 Q3 公司整体期间费用率同比 1 24pct，其中， Q3 同比 1 16pct，拆分来看，2020Q3 销售费用率同比 0 19pct、管理费用率同比 0 06pct、研发费用率同比 0 74pct、财务费用率 0 63pct 人民币汇率影响，产生较大汇兑损失 。2020Q3 经营活动现金流净额同比 8 96 。短期收入及盈利承压，看好中长期网络融合发展考虑到国内用户需求景气度依然偏低，同时低毛利率 ToB 业务占比提升，我们下调了营收、毛利率以及归母净利润，调整了部分费用率指标，预测公司 2020 2022 年 EPS 为 0 53、0 62、0 72 元 前值 0 72、0 83、0 92元 。 截至 2020 年 10 月 26 日， 根据 Wind 一致预期，行业可比公司 2021年平均 PE 为 14x， 短期公司收入及盈利增长虽有压力，但公司为网络智能终端优势企业，具备丰富的运营商渠道资源，仍受益于国内和海外超高清及网络融合产品的更新提速，中长期收入仍有增长空间。认可给予公司 2021年 18x PE，对应目标价格 11 16 元 前值 15 84 元 ，维持 买入 评级。风险提示 政策不确定性 行业竞争加剧 原材料成本波动 疫情蔓延。同时，下面我提供的一份该股票的近期市场数据， 提示:我提供的数据一般是由三个字段组成，分别是每个对应日期的股票价格，涨跌幅，成交量数据。 数据如下: 1.该企业的近期数据如下:1.股票价格（元）:{'2020-10-09': 9.88, '2020-10-12': 10.23, '2020-10-13': 10.19, '2020-10-14': 9.99, '2020-10-15': 9.99, '2020-10-16': 9.84, '2020-10-19': 9.88, '2020-10-20': 10.18, '2020-10-21': 10.07, '2020-10-22': 10.19, '2020-10-23': 10.09, '2020-10-26': 10.12, '2020-10-27': 9.59, '2020-10-28': 9.09, '2020-10-29': 9.02, '2020-10-30': 8.7}; 2.日涨跌幅（%）:{'2020-10-09': 2.9167, '2020-10-12': 3.5425, '2020-10-13': -0.391, '2020-10-14': -1.9627, '2020-10-15': 0.0, '2020-10-16': -1.5015, '2020-10-19': 0.4065, '2020-10-20': 3.0364, '2020-10-21': -1.0806, '2020-10-22': 1.1917, '2020-10-23': -0.9814, '2020-10-26': 0.2973, '2020-10-27': -5.2372, '2020-10-28': -5.2138, '2020-10-29': -0.7701, '2020-10-30': -3.5477}; 3.日成交量（亿):{'2020-10-09': 38623.4, '2020-10-12': 60284.49, '2020-10-13': 38553.26, '2020-10-14': 48751.0, '2020-10-15': 38277.99, '2020-10-16': 43244.48, '2020-10-19': 47258.99, '2020-10-20': 81618.35, '2020-10-21': 48964.42, '2020-10-22': 57686.05, '2020-10-23': 42811.34, '2020-10-26': 30793.35, '2020-10-27': 130922.99, '2020-10-28': 121724.15, '2020-10-29': 78695.4, '2020-10-30': 71291.43}",
        "generated_question": "关于创维数字（000810）的最新研报显示了哪些信息？",
        "trend_keywords": [],
        "year_keywords": [
          "2020",
          "2022",
          "2021"
        ],
        "term_keywords": [
          "收入"
        ],
        "context_trend_score": 0,
        "context_year_score": 3,
        "context_term_score": 1,
        "question_trend_score": 0,
        "question_year_score": 0,
        "question_term_score": 0,
        "trend_score": 0,
        "year_score": 3,
        "term_score": 1,
        "total_score": 4,
        "context_score": 4,
        "diversity_score": 0.0
      },
      {
        "sample_id": "unknown",
        "summary": "这份利润表数据显示了分众传媒在2013年12月31日的财务状况，包括营业收入、营业成本、财务费用等关键指标，以及所得税费用为19,182,472.01。",
        "content": "{'TS代码': '002027.SZ', '实际公告日期': Timestamp('2014-04-28 00:00:00'), '公司类型(1一般工商业2银行3保险4证券)': '1', '营业收入': 255848675.51, '减:营业成本': 292550533.16, '减:营业税金及附加': 110342.33, '减:财务费用': 788526.05, '利润总额': -66267573.79, '所得税费用': 19182472.01, '归属于少数股东的综合收益总额': '-1157120.46', '交易日': '2013-12-31'}。",
        "generated_question": "分众传媒在2013年的所得税费用是多少？",
        "trend_keywords": [],
        "year_keywords": [
          "2013",
          "2014"
        ],
        "term_keywords": [
          "营业收入"
        ],
        "context_trend_score": 0,
        "context_year_score": 2,
        "context_term_score": 1,
        "question_trend_score": 0,
        "question_year_score": 0,
        "question_term_score": 0,
        "trend_score": 0,
        "year_score": 2,
        "term_score": 1,
        "total_score": 3,
        "context_score": 3,
        "diversity_score": 0.0
      },
      {
        "sample_id": "unknown",
        "summary": "立讯精密于2021年6月30日发布的利润表数据显示，其营业总成本为256,325,427,354.55元，其中减去营业成本后的金额为228,699,652,965.8元，资产减值损失为-4,048,920.76元，最终营业利润为1,998,326,683.29元。",
        "content": "{'TS代码': '002475.SZ', '报告期': '20210630', '营业总成本': 25632542735.45, '减:营业成本': 22869965296.58, '减:资产减值损失': '-40489207.65', '营业利润': 1998326683.29, '减:营业外支出': 32721299.46, '净利润(含少数股东损益)': 2004305455.92, '其他综合收益': '28952514.81', '更新标识': '0', '交易日': '2021-06-30'}。",
        "generated_question": "立讯精密（002475.SZ）于2021年6月30日的营业利润是多少？",
        "trend_keywords": [],
        "year_keywords": [
          "2021"
        ],
        "term_keywords": [
          "营业利润",
          "净利润"
        ],
        "context_trend_score": 0,
        "context_year_score": 1,
        "context_term_score": 2,
        "question_trend_score": 0,
        "question_year_score": 0,
        "question_term_score": 0,
        "trend_score": 0,
        "year_score": 1,
        "term_score": 2,
        "total_score": 3,
        "context_score": 3,
        "diversity_score": 0.0
      },
      {
        "sample_id": "unknown",
        "summary": "云南白药公司在2002年3月31日的报告期内，净利润（含少数股东损益）为19,838,873.03元。",
        "content": "{'TS代码': '000538.SZ', '实际公告日期': Timestamp('2002-04-18 00:00:00'), '报告期': '20020331', '公司类型(1一般工商业2银行3保险4证券)': '1', '营业总收入': 226799360.57, '营业总成本': 203380938.69, '营业利润': 23870124.3, '加:营业外收入': 54137.89, '净利润(含少数股东损益)': 19838873.03, '更新标识': '0', '交易日': '2002-03-31'}。",
        "generated_question": "云南白药公司在2002年3月31日的报告期内，净利润（含少数股东损益）是多少？",
        "trend_keywords": [],
        "year_keywords": [
          "2002"
        ],
        "term_keywords": [
          "营业利润",
          "净利润"
        ],
        "context_trend_score": 0,
        "context_year_score": 1,
        "context_term_score": 2,
        "question_trend_score": 0,
        "question_year_score": 0,
        "question_term_score": 1,
        "trend_score": 0,
        "year_score": 1,
        "term_score": 2,
        "total_score": 3,
        "context_score": 3,
        "diversity_score": 0.0
      }
    ]
  },
  "unique_samples": [
    {
      "sample_id": "unknown",
      "summary": "云南白药公司在2002年3月31日的报告期内，净利润（含少数股东损益）为19,838,873.03元。",
      "content": "{'TS代码': '000538.SZ', '实际公告日期': Timestamp('2002-04-18 00:00:00'), '报告期': '20020331', '公司类型(1一般工商业2银行3保险4证券)': '1', '营业总收入': 226799360.57, '营业总成本': 203380938.69, '营业利润': 23870124.3, '加:营业外收入': 54137.89, '净利润(含少数股东损益)': 19838873.03, '更新标识': '0', '交易日': '2002-03-31'}。",
      "generated_question": "云南白药公司在2002年3月31日的报告期内，净利润（含少数股东损益）是多少？",
      "trend_keywords": [],
      "year_keywords": [
        "2002"
      ],
      "term_keywords": [
        "营业利润",
        "净利润"
      ],
      "context_trend_score": 0,
      "context_year_score": 1,
      "context_term_score": 2,
      "question_trend_score": 0,
      "question_year_score": 0,
      "question_term_score": 1,
      "trend_score": 0,
      "year_score": 1,
      "term_score": 2,
      "total_score": 3,
      "context_score": 3,
      "diversity_score": 0.0
    }
  ]
}